Workbook
Name budget: 'BUDGET DASHBOARD'!$L1
Name budget_range: 'BUDGET DASHBOARD'!$Q1
Name budget_rank: 'BUDGET DASHBOARD'!$R1
Name cc_budget: CALCULATIONS!$K1
Name cc_delta: CALCULATIONS!$L1
Name cc_in_focus: CALCULATIONS!$G1
Name cc_month: CALCULATIONS!$F1
Name cc_show_rem_budget: CALCULATIONS!$I1
Name cc_show_type: CALCULATIONS!$H1
Name cc_tracked: CALCULATIONS!$J1
Name cc_type: CALCULATIONS!$E1
Name comb_rank: 'BUDGET DASHBOARD'!$S1
Name comb_rank_norm: 'BUDGET DASHBOARD'!$U1
Name comb_rank_norm_run_range: 'BUDGET DASHBOARD'!$V1
Name comb_rank_range: 'BUDGET DASHBOARD'!$T1
Name comb_rank_unique: 'BUDGET DASHBOARD'!$W1
Name current_date: DATE(2022,3,15)
Name EXPENSES: 'BUDGET PLANNING'!$D$42
Name expenses_header_row: ROW('BUDGET PLANNING'!$C$22)
Name EXPENSES_MAX_ROW: MAX(ROW(EXPENSES))
Name EXPENSES_MIN_ROW: MIN(ROW(EXPENSES))
Name EXPENSES_TOTAL_ROW: ROW('BUDGET PLANNING'!#REF!)
Name header_row_id: 'BUDGET DASHBOARD'!$D1
Name INCOME: 'BUDGET PLANNING'!$C$9
Name INCOME_HEADER_ROW: ROW('BUDGET PLANNING'!$C$9)
Name INCOME_MAX_ROW: MAX(ROW(INCOME))
Name INCOME_MIN_ROW: MIN(ROW(INCOME))
Name INCOME_TOTAL_ROW: ROW('BUDGET PLANNING'!$C$20)
Name is_cat: 'BUDGET DASHBOARD'!$F1
Name is_empty: 'BUDGET DASHBOARD'!$H1
Name is_header: 'BUDGET DASHBOARD'!$E1
Name is_total: 'BUDGET DASHBOARD'!$G1
Name item: 'BUDGET DASHBOARD'!$J1
Name out_budget: 'BUDGET DASHBOARD'!$AA1
Name out_percentage_completed: 'BUDGET DASHBOARD'!$AB1
Name out_tracked: 'BUDGET DASHBOARD'!$Z1
Name row_id: 'BUDGET DASHBOARD'!$C1
Name SAVINGS: 'BUDGET PLANNING'!$K$52
Name SAVINGS_HEADER_ROW: ROW(SAVINGS('BUDGET PLANNING'!$C$48))
Name SAVINGS_MAX_ROW: MAX(ROW('BUDGET PLANNING'!$C$48))
Name SAVINGS_MIN_ROW: MIN(ROW('BUDGET PLANNING'!$C$48))
Name SAVINGS_TOTAL_ROW: TOTAL(ROW('BUDGET PLANNING'!$C$55))
Name selected_period: CALCULATIONS!$E$20
Name selected_period_display: CALCULATIONS!$E$21
Name selected_year: CALCULATIONS!$E$19
Name Shift_late_income_starting_day: SETTINGS!$E$18
Name Shift_late_income_status: SETTINGS!$E$18
Name shift_late_income_status_2: SETTINGS!$E$16
Name sort_max_row: 'BUDGET DASHBOARD'!$N1
Name sort_min_row: 'BUDGET DASHBOARD'!$M1
Name STARTING_ON_DAY_X_IN_MONTH: SETTINGS!$E$18
Name STARTING_YEAR: SETTINGS!$E$8
Name tracked: 'BUDGET DASHBOARD'!$K1
Name tracked_range: 'BUDGET DASHBOARD'!$O1
Name tracked_rank: 'BUDGET DASHBOARD'!$P1
Name tracking1: TRACKING[#All]
Name type: 'BUDGET DASHBOARD'!$I1

Sheet SETTINGS
C6: GENERAL
D8: STARTING YEAR:- | E8: 2022 | G8: Set the starting year(yyyy)once at the beginning and do not change it again.
C12: BUDGET TRACKING & DASHBOARD
D14: LATE MONTHLY INCOME
D16: SHIFT LATE INCOME: | E16: Active | G16: Activate this option to treat late income received on or after a certain day of the month as income for the next month.This is especially recommended in case you receive your monthly paycheck towards the end of the month and prefer to consider this income as the disposable income for the next month.
D18: STARTING ON DAY X IN MONTH: | E18: 20

Sheet BUDGET PLANNING
A1: BUDGET PLANNING
C5: Define starting year in settings | E5: =STARTING_YEAR -> 2022 | S5: =E5+1 -> 2023 | AG5: =S5+1 -> 2024 | AU5: =AG5+1 -> 2025
E6: =IF(E7=0,"Jan √","Jan") -> Jan √ | F6: =IF(F7=0,"Feb √","Feb") -> Feb √ | G6: =IF(G7=0,"Mar √","Mar") -> Mar √ | H6: =IF(H7=0,"Apr √","Apr") -> Apr √ | I6: =IF(I7=0,"May √","May") -> May √ | J6: =IF(J7=0,"Jun √","Jun") -> Jun √ | K6: =IF(K7=0,"Jul √","Jul") -> Jul √ | L6: =IF(L7=0,"Aug √","Aug") -> Aug √ | M6: =IF(M7=0,"Sep √","Sep") -> Sep √ | N6: =IF(N7=0,"Oct √","Oct") -> Oct √ | O6: =IF(O7=0,"Nov √","Nov") -> Nov √ | P6: =IF(P7=0,"Dec √","Dec") -> Dec √ | Q6: =IF(Q7=0,"Total √","Total") -> Total √ | S6: =IF(S7=0,"Jan √","Jan") -> Jan √ | T6: =IF(T7=0,"Feb √","Feb") -> Feb √ | U6: =IF(U7=0,"Mar √","Mar") -> Mar √ | V6: =IF(V7=0,"Apr √","Apr") -> Apr √ | W6: =IF(W7=0,"May √","May") -> May √ | X6: =IF(X7=0,"Jun √","Jun") -> Jun √ | Y6: =IF(Y7=0,"Jul √","Jul") -> Jul √ | Z6: =IF(Z7=0,"Aug √","Aug") -> Aug √ | AA6: =IF(AA7=0,"Sep √","Sep") -> Sep √ | AB6: =IF(AB7=0,"Oct √","Oct") -> Oct √ | AC6: =IF(AC7=0,"Nov √","Nov") -> Nov √ | AD6: =IF(AD7=0,"Dec √","Dec") -> Dec √ | AE6: =IF(AE7=0,"Total √","Total") -> Total √ | AG6: =IF(AG7=0,"Jan √","Jan") -> Jan √ | AH6: =IF(AH7=0,"Feb √","Feb") -> Feb √ | AI6: =IF(AI7=0,"Mar √","Mar") -> Mar √ | AJ6: =IF(AJ7=0,"Apr √","Apr") -> Apr √ | AK6: =IF(AK7=0,"May √","May") -> May √ | AL6: =IF(AL7=0,"Jun √","Jun") -> Jun √ | AM6: =IF(AM7=0,"Jul √","Jul") -> Jul √ | AN6: =IF(AN7=0,"Aug √","Aug") -> Aug √ | AO6: =IF(AO7=0,"Sep √","Sep") -> Sep √ | AP6: =IF(AP7=0,"Oct √","Oct") -> Oct √ | AQ6: =IF(AQ7=0,"Nov √","Nov") -> Nov √ | AR6: =IF(AR7=0,"Dec √","Dec") -> Dec √ | AS6: =IF(AS7=0,"Total √","Total") -> Total √ | AU6: =IF(AU7=0,"Jan √","Jan") -> Jan √ | AV6: =IF(AV7=0,"Feb √","Feb") -> Feb √ | AW6: =IF(AW7=0,"Mar √","Mar") -> Mar √ | AX6: =IF(AX7=0,"Apr √","Apr") -> Apr √ | AY6: =IF(AY7=0,"May √","May") -> May √ | AZ6: =IF(AZ7=0,"Jun √","Jun") -> Jun √ | BA6: =IF(BA7=0,"Jul √","Jul") -> Jul √ | BB6: =IF(BB7=0,"Aug √","Aug") -> Aug √ | BC6: =IF(BC7=0,"Sep √","Sep") -> Sep √ | BD6: =IF(BD7=0,"Oct √","Oct") -> Oct √ | BE6: =IF(BE7=0,"Nov √","Nov") -> Nov √ | BF6: =IF(BF7=0,"Dec √","Dec") -> Dec √ | BG6: =IF(BG7=0,"Total √","Total") -> Total √
C7: TO BE ALLOCATED:- | E7: =E20-(E41+E55) -> 0 | F7: =F20-(F41+F55) -> 0 | G7: =G20-(G41+G55) -> 0 | H7: =H20-(H41+H55) -> 0 | I7: =I20-(I41+I55) -> 0 | J7: =J20-(J41+J55) -> 0 | K7: =K20-(K41+K55) -> 0 | M7: =M20-(M41+M55) -> 0 | N7: =N20-(N41+N55) -> 0 | O7: =O20-(O41+O55) -> 0 | P7: =P20-(P41+P55) -> 0 | S7: =S20-(S41+S55) -> 0 | T7: =T20-(T41+T55) -> 0 | U7: =U20-(U41+U55) -> 0 | V7: =V20-(V41+V55) -> 0 | W7: =W20-(W41+W55) -> 0 | X7: =X20-(X41+X55) -> 0 | Y7: =Y20-(Y41+Y55) -> 0 | Z7: =Z20-(Z41+Z55) -> 0 | ... AE7: =AE20-(AE41+AE55) -> 0 | AG7: =AG20-(AG41+AG55) -> 0 | AH7: =AH20-(AH41+AH55) -> 0 | AI7: =AI20-(AI41+AI55) -> 0 | AJ7: =AJ20-(AJ41+AJ55) -> 0 | AK7: =AK20-(AK41+AK55) -> 0 | AL7: =AL20-(AL41+AL55) -> 0 | AM7: =AM20-(AM41+AM55) -> 0 | AN7: =AN20-(AN41+AN55) -> 0 | ... AS7: =AS20-(AS41+AS55) -> 0 | AU7: =AU20-(AU41+AU55) -> 0 | AV7: =AV20-(AV41+AV55) -> 0 | AW7: =AW20-(AW41+AW55) -> 0 | AX7: =AX20-(AX41+AX55) -> 0 | AY7: =AY20-(AY41+AY55) -> 0 | AZ7: =AZ20-(AZ41+AZ55) -> 0 | BA7: =BA20-(BA41+BA55) -> 0 | BB7: =BB20-(BB41+BB55) -> 0 | ... BG7: =BG20-(BG41+BG55) -> 0
C9: INCOME | E9: =DATE(E$5,1,1) -> 44562 | F9: =DATE(E$5,2,1) -> 44593 | G9: =DATE(E$5,3,1) -> 44621 | H9: =DATE(E$5,4,1) -> 44652 | I9: =DATE(E$5,5,1) -> 44682 | J9: =DATE(E$5,6,1) -> 44713 | K9: =DATE(E$5,7,1) -> 44743 | L9: =DATE(E$5,8,1) -> 44774 | M9: =DATE(E$5,9,1) -> 44805 | N9: =DATE(E$5,10,1) -> 44835 | O9: =DATE(E$5,11,1) -> 44866 | P9: =DATE(E$5,12,1) -> 44896 | Q9: =E8 -> 0 | S9: =DATE(S$5,1,1) -> 44927 | T9: =DATE(S$5,2,1) -> 44958 | U9: =DATE(S$5,3,1) -> 44986 | V9: =DATE(S$5,4,1) -> 45017 | W9: =DATE(S$5,5,1) -> 45047 | X9: =DATE(S$5,6,1) -> 45078 | Y9: =DATE(S$5,7,1) -> 45108 | Z9: =DATE(S$5,8,1) -> 45139 | AA9: =DATE(S$5,9,1) -> 45170 | AB9: =DATE(S$5,10,1) -> 45200 | AC9: =DATE(S$5,11,1) -> 45231 | AD9: =DATE(S$5,12,1) -> 45261 | AE9: =S8 -> 0 | AG9: =DATE(AG$5,1,1) -> 45292 | AH9: =DATE(AG$5,2,1) -> 45323 | AI9: =DATE(AG$5,3,1) -> 45352 | AJ9: =DATE(AG$5,4,1) -> 45383 | AK9: =DATE(AG$5,5,1) -> 45413 | AL9: =DATE(AG$5,6,1) -> 45444 | AM9: =DATE(AG$5,7,1) -> 45474 | AN9: =DATE(AG$5,8,1) -> 45505 | AO9: =DATE(AG$5,9,1) -> 45536 | AP9: =DATE(AG$5,10,1) -> 45566 | AQ9: =DATE(AG$5,11,1) -> 45597 | AR9: =DATE(AG$5,12,1) -> 45627 | AS9: =AG8 -> 0 | AU9: =DATE(AU$5,1,1) -> 45658 | AV9: =DATE(AU$5,2,1) -> 45689 | AW9: =DATE(AU$5,3,1) -> 45717 | AX9: =DATE(AU$5,4,1) -> 45748 | AY9: =DATE(AU$5,5,1) -> 45778 | AZ9: =DATE(AU$5,6,1) -> 45809 | BA9: =DATE(AU$5,7,1) -> 45839 | BB9: =DATE(AU$5,8,1) -> 45870 | BC9: =DATE(AU$5,9,1) -> 45901 | BD9: =DATE(AU$5,10,1) -> 45931 | BE9: =DATE(AU$5,11,1) -> 45962 | BF9: =DATE(AU$5,12,1) -> 45992 | BG9: =AU8 -> 0
C10: EMPLOYMENT(NET) | E10: 3500 | F10: 3500 | G10: 3500 | H10: 4500 | I10: 4500 | J10: 4500 | K10: 4500 | L10: 4500 | M10: 4500 | N10: 4500 | O10: 4500 | P10: 4500 | Q10: =SUM(E10:P10) -> 51000 | AE10: =SUM(S10:AD10) -> 0 | AS10: =SUM(AG10:AR10) -> 0 | BG10: =SUM(AU10:BF10) -> 0
C11: SIDE HUSTLE(NET) | E11: 1000 | F11: 1000 | G11: 1000 | H11: 1000 | I11: 1000 | J11: 1000 | K11: 1000 | L11: 1000 | M11: 1000 | N11: 1000 | O11: 1000 | P11: 1000 | Q11: =SUM(E11:P11) -> 12000 | AE11: =SUM(S11:AD11) -> 0 | AS11: =SUM(AG11:AR11) -> 0 | BG11: =SUM(AU11:BF11) -> 0
C12: DIVIDENDS | E12: 150 | F12: 50 | G12: 100 | H12: 150 | I12: 50 | J12: 100 | K12: 150 | L12: 50 | M12: 100 | N12: 150 | O12: 50 | P12: 100 | Q12: =SUM(E12:P12) -> 1200 | AE12: =SUM(S12:AD12) -> 0 | AS12: =SUM(AG12:AR12) -> 0 | BG12: =SUM(AU12:BF12) -> 0
C13: ENTER INCOME CATEGORY…. | AE13: =SUM(S13:AD13) -> 0 | AS13: =SUM(AG13:AR13) -> 0 | BG13: =SUM(AU13:BF13) -> 0
C14: ENTER INCOME CATEGORY…. | AE14: =SUM(S14:AD14) -> 0 | AS14: =SUM(AG14:AR14) -> 0 | BG14: =SUM(AU14:BF14) -> 0
C15: ENTER INCOME CATEGORY…. | AE15: =SUM(S15:AD15) -> 0 | AS15: =SUM(AG15:AR15) -> 0 | BG15: =SUM(AU15:BF15) -> 0
C16: ENTER INCOME CATEGORY…. | AE16: =SUM(S16:AD16) -> 0 | AS16: =SUM(AG16:AR16) -> 0 | BG16: =SUM(AU16:BF16) -> 0
C17: ENTER INCOME CATEGORY…. | AE17: =SUM(S17:AD17) -> 0 | AS17: =SUM(AG17:AR17) -> 0 | BG17: =SUM(AU17:BF17) -> 0
C18: ENTER INCOME CATEGORY…. | AE18: =SUM(S18:AD18) -> 0 | AS18: =SUM(AG18:AR18) -> 0 | BG18: =SUM(AU18:BF18) -> 0
C19: ENTER INCOME CATEGORY…. | AE19: =SUM(S19:AD19) -> 0 | AS19: =SUM(AG19:AR19) -> 0 | BG19: =SUM(AU19:BF19) -> 0
C20: TOTAL | E20: =SUM(E10:E12) -> 4650 | F20: =SUM(F10:F12) -> 4550 | G20: =SUM(G10:G12) -> 4600 | H20: =SUM(H10:H12) -> 5650 | I20: =SUM(I10:I12) -> 5550 | J20: =SUM(J10:J12) -> 5600 | K20: =SUM(K10:K12) -> 5650 | L20: =SUM(L10:L12) -> 5550 | ... P20: =SUM(P10:P12) -> 5600 | Q20: =SUM(E20:P20) -> 64200 | S20: =SUM(S10:S12) -> 0 | T20: =SUM(T10:T12) -> 0 | U20: =SUM(U10:U12) -> 0 | V20: =SUM(V10:V12) -> 0 | W20: =SUM(W10:W12) -> 0 | X20: =SUM(X10:X12) -> 0 | Y20: =SUM(Y10:Y12) -> 0 | Z20: =SUM(Z10:Z12) -> 0 | ... AD20: =SUM(AD10:AD12) -> 0 | AE20: =SUM(S20:AD20) -> 0 | AG20: =SUM(AG10:AG12) -> 0 | AH20: =SUM(AH10:AH12) -> 0 | AI20: =SUM(AI10:AI12) -> 0 | AJ20: =SUM(AJ10:AJ12) -> 0 | AK20: =SUM(AK10:AK12) -> 0 | AL20: =SUM(AL10:AL12) -> 0 | AM20: =SUM(AM10:AM12) -> 0 | AN20: =SUM(AN10:AN12) -> 0 | ... AR20: =SUM(AR10:AR12) -> 0 | AS20: =SUM(AG20:AR20) -> 0 | AU20: =SUM(AU10:AU12) -> 0 | AV20: =SUM(AV10:AV12) -> 0 | AW20: =SUM(AW10:AW12) -> 0 | AX20: =SUM(AX10:AX12) -> 0 | AY20: =SUM(AY10:AY12) -> 0 | AZ20: =SUM(AZ10:AZ12) -> 0 | BA20: =SUM(BA10:BA12) -> 0 | BB20: =SUM(BB10:BB12) -> 0 | ... BF20: =SUM(BF10:BF12) -> 0 | BG20: =SUM(AU20:BF20) -> 0
C22: EXPENSES | E22: =DATE(E$5,1,1) -> 44562 | F22: =DATE(E$5,2,1) -> 44593 | G22: =DATE(E$5,3,1) -> 44621 | H22: =DATE(E$5,4,1) -> 44652 | I22: =DATE(E$5,5,1) -> 44682 | J22: =DATE(E$5,6,1) -> 44713 | K22: =DATE(E$5,7,1) -> 44743 | L22: =DATE(E$5,8,1) -> 44774 | M22: =DATE(E$5,9,1) -> 44805 | N22: =DATE(E$5,10,1) -> 44835 | O22: =DATE(E$5,11,1) -> 44866 | P22: =DATE(E$5,12,1) -> 44896 | Q22: =E21 -> 0 | S22: Jan | T22: =DATE(S$5,2,1) -> 44958 | U22: =DATE(S$5,3,1) -> 44986 | V22: =DATE(S$5,4,1) -> 45017 | W22: =DATE(S$5,5,1) -> 45047 | X22: =DATE(S$5,6,1) -> 45078 | Y22: =DATE(S$5,7,1) -> 45108 | Z22: Aug | AA22: =DATE(S$5,9,1) -> 45170 | AB22: =DATE(S$5,10,1) -> 45200 | AC22: =DATE(S$5,11,1) -> 45231 | AD22: =DATE(S$5,12,1) -> 45261 | AE22: =S21 -> 0 | AG22: Jan | AH22: =DATE(AG$5,2,1) -> 45323 | AI22: =DATE(AG$5,3,1) -> 45352 | AJ22: =DATE(AG$5,4,1) -> 45383 | AK22: =DATE(AG$5,5,1) -> 45413 | AL22: =DATE(AG$5,6,1) -> 45444 | AM22: =DATE(AG$5,7,1) -> 45474 | AN22: Aug | AO22: =DATE(AG$5,9,1) -> 45536 | AP22: =DATE(AG$5,10,1) -> 45566 | AQ22: =DATE(AG$5,11,1) -> 45597 | AR22: =DATE(AG$5,12,1) -> 45627 | AS22: =AG21 -> 0 | AU22: Jan | AV22: =DATE(AU$5,2,1) -> 45689 | AW22: =DATE(AU$5,3,1) -> 45717 | AX22: =DATE(AU$5,4,1) -> 45748 | AY22: =DATE(AU$5,5,1) -> 45778 | AZ22: =DATE(AU$5,6,1) -> 45809 | BA22: =DATE(AU$5,7,1) -> 45839 | BB22: Aug | BC22: =DATE(AU$5,9,1) -> 45901 | BD22: =DATE(AU$5,10,1) -> 45931 | BE22: =DATE(AU$5,11,1) -> 45962 | BF22: =DATE(AU$5,12,1) -> 45992 | BG22: =AU21 -> 0
C26: HOUSING | E26: 1200 | F26: 1200 | G26: 1200 | H26: 1200 | I26: 1200 | J26: 1200 | K26: 1200 | L26: 1200 | M26: 1200 | N26: 1200 | O26: 1200 | P26: 1200 | Q26: =SUM(E26:P26) -> 14400 | AE26: =SUM(S26:AD26) -> 0 | AS26: =SUM(AG26:AR26) -> 0 | BG26: =SUM(AU26:BF26) -> 0
Q27: =SUM(E27:P27) -> 0 | AE27: =SUM(S27:AD27) -> 0 | AS27: =SUM(AG27:AR27) -> 0 | BG27: =SUM(AU27:BF27) -> 0
Q28: =SUM(E28:P28) -> 0 | AE28: =SUM(S28:AD28) -> 0 | AS28: =SUM(AG28:AR28) -> 0 | BG28: =SUM(AU28:BF28) -> 0
Q29: =SUM(E29:P29) -> 0 | AE29: =SUM(S29:AD29) -> 0 | AS29: =SUM(AG29:AR29) -> 0 | BG29: =SUM(AU29:BF29) -> 0
Q30: =SUM(E30:P30) -> 0 | AE30: =SUM(S30:AD30) -> 0 | AS30: =SUM(AG30:AR30) -> 0 | BG30: =SUM(AU30:BF30) -> 0
Q31: =SUM(E31:P31) -> 0 | AE31: =SUM(S31:AD31) -> 0 | AS31: =SUM(AG31:AR31) -> 0 | BG31: =SUM(AU31:BF31) -> 0
C32: UTITLITIES | E32: 300 | F32: 300 | G32: 300 | H32: 300 | I32: 300 | J32: 300 | K32: 300 | L32: 300 | M32: 300 | N32: 300 | O32: 300 | P32: 300 | Q32: =SUM(E32:P32) -> 3600 | AE32: =SUM(S32:AD32) -> 0 | AS32: =SUM(AG32:AR32) -> 0 | BG32: =SUM(AU32:BF32) -> 0
C33: GROCERIES | E33: 350 | F33: 350 | G33: 350 | H33: 350 | I33: 350 | J33: 350 | K33: 350 | L33: 350 | M33: 350 | N33: 350 | O33: 350 | P33: 350 | Q33: =SUM(E33:P33) -> 4200 | AE33: =SUM(S33:AD33) -> 0 | AS33: =SUM(AG33:AR33) -> 0 | BG33: =SUM(AU33:BF33) -> 0
C34: TRANSPORTATION | E34: 300 | F34: 300 | G34: 300 | H34: 300 | I34: 300 | J34: 300 | K34: 300 | L34: 300 | M34: 300 | N34: 300 | O34: 300 | P34: 300 | Q34: =SUM(E34:P34) -> 3600 | AE34: =SUM(S34:AD34) -> 0 | AS34: =SUM(AG34:AR34) -> 0 | BG34: =SUM(AU34:BF34) -> 0
C35: INSURANCES | G35: 150 | J35: 150 | M35: 150 | P35: 150 | Q35: =SUM(E35:P35) -> 600 | AE35: =SUM(S35:AD35) -> 0 | AS35: =SUM(AG35:AR35) -> 0 | BG35: =SUM(AU35:BF35) -> 0
C36: CLOTHING | E36: 200 | F36: 200 | G36: 200 | H36: 200 | I36: 200 | J36: 200 | K36: 200 | L36: 200 | M36: 200 | N36: 200 | O36: 200 | P36: 200 | Q36: =SUM(E36:P36) -> 2400 | AE36: =SUM(S36:AD36) -> 0 | AS36: =SUM(AG36:AR36) -> 0 | BG36: =SUM(AU36:BF36) -> 0
C37: BODY CARE AND MEDICINE | E37: 200 | F37: 200 | G37: 200 | H37: 200 | I37: 200 | J37: 200 | K37: 200 | L37: 200 | M37: 200 | N37: 200 | O37: 200 | P37: 200 | Q37: =SUM(E37:P37) -> 2400 | AE37: =SUM(S37:AD37) -> 0 | AS37: =SUM(AG37:AR37) -> 0 | BG37: =SUM(AU37:BF37) -> 0
C38: MEDIA | E38: 50 | F38: 50 | G38: 50 | H38: 50 | I38: 50 | J38: 50 | K38: 50 | L38: 50 | M38: 50 | N38: 50 | O38: 50 | P38: 50 | Q38: =SUM(E38:P38) -> 600 | AE38: =SUM(S38:AD38) -> 0 | AS38: =SUM(AG38:AR38) -> 0 | BG38: =SUM(AU38:BF38) -> 0
C39: FUN And VACATION | E39: 300 | F39: 300 | G39: 300 | H39: 1200 | I39: 300 | J39: 300 | K39: 300 | L39: 50 | M39: 300 | N39: 300 | O39: 300 | P39: 600 | Q39: =SUM(E39:P39) -> 4550 | AE39: =SUM(S39:AD39) -> 0 | AS39: =SUM(AG39:AR39) -> 0 | BG39: =SUM(AU39:BF39) -> 0
Q40: =SUM(E40:P40) -> 0 | AE40: =SUM(S40:AD40) -> 0 | AS40: =SUM(AG40:AR40) -> 0 | BG40: =SUM(AU40:BF40) -> 0
C41: TOTAL | E41: =SUM(E26:E39) -> 2900 | F41: =SUM(F26:F39) -> 2900 | G41: =SUM(G26:G39) -> 3050 | H41: =SUM(H26:H39) -> 3800 | I41: =SUM(I26:I39) -> 2900 | J41: =SUM(J26:J39) -> 3050 | K41: =SUM(K26:K39) -> 2900 | L41: =SUM(L26:L39) -> 2650 | ... P41: =SUM(P26:P39) -> 3350 | Q41: =SUM(E41:P41) -> 36350 | S41: =SUM(S26:S39) -> 0 | T41: =SUM(T26:T39) -> 0 | U41: =SUM(U26:U39) -> 0 | V41: =SUM(V26:V39) -> 0 | W41: =SUM(W26:W39) -> 0 | X41: =SUM(X26:X39) -> 0 | Y41: =SUM(Y26:Y39) -> 0 | Z41: =SUM(Z26:Z39) -> 0 | ... AD41: =SUM(AD26:AD39) -> 0 | AE41: =SUM(S41:AD41) -> 0 | AG41: =SUM(AG26:AG39) -> 0 | AH41: =SUM(AH26:AH39) -> 0 | AI41: =SUM(AI26:AI39) -> 0 | AJ41: =SUM(AJ26:AJ39) -> 0 | AK41: =SUM(AK26:AK39) -> 0 | AL41: =SUM(AL26:AL39) -> 0 | AM41: =SUM(AM26:AM39) -> 0 | AN41: =SUM(AN26:AN39) -> 0 | ... AR41: =SUM(AR26:AR39) -> 0 | AS41: =SUM(AG41:AR41) -> 0 | AU41: =SUM(AU26:AU39) -> 0 | AV41: =SUM(AV26:AV39) -> 0 | AW41: =SUM(AW26:AW39) -> 0 | AX41: =SUM(AX26:AX39) -> 0 | AY41: =SUM(AY26:AY39) -> 0 | AZ41: =SUM(AZ26:AZ39) -> 0 | BA41: =SUM(BA26:BA39) -> 0 | BB41: =SUM(BB26:BB39) -> 0 | ... BF41: =SUM(BF26:BF39) -> 0 | BG41: =SUM(AU41:BF41) -> 0
C43: EXPENSES | E43: =DATE(E$5,1,1) -> 44562 | F43: =DATE(E$5,2,1) -> 44593 | G43: =DATE(E$5,3,1) -> 44621 | H43: =DATE(E$5,4,1) -> 44652 | I43: =DATE(E$5,5,1) -> 44682 | J43: =DATE(E$5,6,1) -> 44713 | K43: =DATE(E$5,7,1) -> 44743 | L43: =DATE(E$5,8,1) -> 44774 | M43: =DATE(E$5,9,1) -> 44805 | N43: =DATE(E$5,10,1) -> 44835 | O43: =DATE(E$5,11,1) -> 44866 | P43: =DATE(E$5,12,1) -> 44896 | Q43: =E42 -> 0 | S43: =DATE(S$5,1,1) -> 44927 | T43: =DATE(S$5,2,1) -> 44958 | U43: =DATE(S$5,3,1) -> 44986 | V43: =DATE(S$5,4,1) -> 45017 | W43: =DATE(S$5,5,1) -> 45047 | X43: =DATE(S$5,6,1) -> 45078 | Y43: =DATE(S$5,7,1) -> 45108 | Z43: =DATE(S$5,8,1) -> 45139 | AA43: =DATE(S$5,9,1) -> 45170 | AB43: =DATE(S$5,10,1) -> 45200 | AC43: =DATE(S$5,11,1) -> 45231 | AD43: =DATE(S$5,12,1) -> 45261 | AE43: =S42 -> 0 | AG43: =DATE(AG$5,1,1) -> 45292 | AH43: =DATE(AG$5,2,1) -> 45323 | AI43: =DATE(AG$5,3,1) -> 45352 | AJ43: =DATE(AG$5,4,1) -> 45383 | AK43: =DATE(AG$5,5,1) -> 45413 | AL43: =DATE(AG$5,6,1) -> 45444 | AM43: =DATE(AG$5,7,1) -> 45474 | AN43: =DATE(AG$5,8,1) -> 45505 | AO43: =DATE(AG$5,9,1) -> 45536 | AP43: =DATE(AG$5,10,1) -> 45566 | AQ43: =DATE(AG$5,11,1) -> 45597 | AR43: =DATE(AG$5,12,1) -> 45627 | AS43: =AG42 -> 0 | AU43: =DATE(AU$5,1,1) -> 45658 | AV43: =DATE(AU$5,2,1) -> 45689 | AW43: =DATE(AU$5,3,1) -> 45717 | AX43: =DATE(AU$5,4,1) -> 45748 | AY43: =DATE(AU$5,5,1) -> 45778 | AZ43: =DATE(AU$5,6,1) -> 45809 | BA43: =DATE(AU$5,7,1) -> 45839 | BB43: =DATE(AU$5,8,1) -> 45870 | BC43: =DATE(AU$5,9,1) -> 45901 | BD43: =DATE(AU$5,10,1) -> 45931 | BE43: =DATE(AU$5,11,1) -> 45962 | BF43: =DATE(AU$5,12,1) -> 45992 | BG43: =AU42 -> 0
C44: HOUSING
C45: UTILITIES
C46: GROCERIES
C48: SAVINGS | E48: =DATE(E$5,1,1) -> 44562 | F48: =DATE(E$5,2,1) -> 44593 | G48: =DATE(E$5,3,1) -> 44621 | H48: =DATE(E$5,4,1) -> 44652 | I48: =DATE(E$5,5,1) -> 44682 | J48: =DATE(E$5,6,1) -> 44713 | K48: =DATE(E$5,7,1) -> 44743 | L48: =DATE(E$5,8,1) -> 44774 | M48: =DATE(E$5,9,1) -> 44805 | N48: =DATE(E$5,10,1) -> 44835 | O48: =DATE(E$5,11,1) -> 44866 | P48: =DATE(E$5,12,1) -> 44896 | Q48: =E47 -> 0 | S48: =DATE(S$5,1,1) -> 44927 | T48: =DATE(S$5,2,1) -> 44958 | U48: =DATE(S$5,3,1) -> 44986 | V48: =DATE(S$5,4,1) -> 45017 | W48: =DATE(S$5,5,1) -> 45047 | X48: =DATE(S$5,6,1) -> 45078 | Y48: =DATE(S$5,7,1) -> 45108 | Z48: =DATE(S$5,8,1) -> 45139 | AA48: =DATE(S$5,9,1) -> 45170 | AB48: =DATE(S$5,10,1) -> 45200 | AC48: =DATE(S$5,11,1) -> 45231 | AD48: =DATE(S$5,12,1) -> 45261 | AE48: =S47 -> 0 | AG48: =DATE(AG$5,1,1) -> 45292 | AH48: =DATE(AG$5,2,1) -> 45323 | AI48: =DATE(AG$5,3,1) -> 45352 | AJ48: =DATE(AG$5,4,1) -> 45383 | AK48: =DATE(AG$5,5,1) -> 45413 | AL48: =DATE(AG$5,6,1) -> 45444 | AM48: =DATE(AG$5,7,1) -> 45474 | AN48: =DATE(AG$5,8,1) -> 45505 | AO48: =DATE(AG$5,9,1) -> 45536 | AP48: =DATE(AG$5,10,1) -> 45566 | AQ48: =DATE(AG$5,11,1) -> 45597 | AR48: =DATE(AG$5,12,1) -> 45627 | AS48: =AG47 -> 0 | AU48: =DATE(AU$5,1,1) -> 45658 | AV48: =DATE(AU$5,2,1) -> 45689 | AW48: =DATE(AU$5,3,1) -> 45717 | AX48: =DATE(AU$5,4,1) -> 45748 | AY48: =DATE(AU$5,5,1) -> 45778 | AZ48: =DATE(AU$5,6,1) -> 45809 | BA48: =DATE(AU$5,7,1) -> 45839 | BB48: =DATE(AU$5,8,1) -> 45870 | BC48: =DATE(AU$5,9,1) -> 45901 | BD48: =DATE(AU$5,10,1) -> 45931 | BE48: =DATE(AU$5,11,1) -> 45962 | BF48: =DATE(AU$5,12,1) -> 45992 | BG48: =AU47 -> 0
C49: EMERGENCY FUND | E49: 1000 | F49: 1000 | G49: 1000 | H49: 0 | I49: 0 | J49: 0 | K49: 0 | L49: 0 | M49: 0 | N49: 0 | O49: 0 | P49: 0 | Q49: =SUM(E49:P49) -> 3000 | AE49: =SUM(S49:AD49) -> 0 | AS49: =SUM(AG49:AR49) -> 0 | BG49: =SUM(AU49:BF49) -> 0
C50: RETIREMENT ACCOUNT | E50: 400 | F50: 400 | G50: 400 | H50: 400 | I50: 400 | J50: 400 | K50: 400 | L50: 400 | M50: 400 | N50: 400 | O50: 400 | P50: 400 | Q50: =SUM(E50:P50) -> 4800 | AE50: =SUM(S50:AD50) -> 0 | AS50: =SUM(AG50:AR50) -> 0 | BG50: =SUM(AU50:BF50) -> 0
C51: STOCK PORTFOLIO | E51: 150 | F51: 150 | G51: 150 | H51: 750 | I51: 750 | J51: 750 | K51: 750 | L51: 750 | M51: 750 | N51: 750 | O51: 750 | P51: 750 | Q51: =SUM(E51:P51) -> 7200 | AE51: =SUM(S51:AD51) -> 0 | AS51: =SUM(AG51:AR51) -> 0 | BG51: =SUM(AU51:BF51) -> 0
C52: SINKING FUND DOWN PAYMENT | E52: 0 | F52: 0 | G52: 0 | H52: 600 | I52: 1400 | J52: 1300 | K52: 1500 | L52: 200 | M52: 1300 | N52: 1500 | O52: 1400 | P52: 1000 | Q52: =SUM(E52:P52) -> 10200 | AE52: =SUM(S52:AD52) -> 0 | AS52: =SUM(AG52:AR52) -> 0 | BG52: =SUM(AU52:BF52) -> 0
C53: SINKING FUND REST | E53: 200 | F53: 100 | G53: 0 | H53: 100 | I53: 100 | J53: 100 | K53: 100 | L53: 100 | M53: 100 | N53: 100 | O53: 100 | P53: 100 | Q53: =SUM(E53:P53) -> 1200 | AE53: =SUM(S53:AD53) -> 0 | AS53: =SUM(AG53:AR53) -> 0 | BG53: =SUM(AU53:BF53) -> 0
Q54: =SUM(E54:P54) -> 0 | AE54: =SUM(S54:AD54) -> 0 | AS54: =SUM(AG54:AR54) -> 0 | BG54: =SUM(AU54:BF54) -> 0
C55: TOTAL | E55: =SUM(E49:E53) -> 1750 | F55: =SUM(F49:F53) -> 1650 | G55: =SUM(G49:G53) -> 1550 | H55: =SUM(H49:H53) -> 1850 | I55: =SUM(I49:I53) -> 2650 | J55: =SUM(J49:J53) -> 2550 | K55: =SUM(K49:K53) -> 2750 | L55: =SUM(L49:L53) -> 1450 | ... P55: =SUM(P49:P53) -> 2250 | Q55: =SUM(E55:P55) -> 26400 | S55: =SUM(S49:S53) -> 0 | T55: =SUM(T49:T53) -> 0 | U55: =SUM(U49:U53) -> 0 | V55: =SUM(V49:V53) -> 0 | W55: =SUM(W49:W53) -> 0 | X55: =SUM(X49:X53) -> 0 | Y55: =SUM(Y49:Y53) -> 0 | Z55: =SUM(Z49:Z53) -> 0 | ... AD55: =SUM(AD49:AD53) -> 0 | AE55: =SUM(S55:AD55) -> 0 | AG55: =SUM(AG49:AG53) -> 0 | AH55: =SUM(AH49:AH53) -> 0 | AI55: =SUM(AI49:AI53) -> 0 | AJ55: =SUM(AJ49:AJ53) -> 0 | AK55: =SUM(AK49:AK53) -> 0 | AL55: =SUM(AL49:AL53) -> 0 | AM55: =SUM(AM49:AM53) -> 0 | AN55: =SUM(AN49:AN53) -> 0 | ... AR55: =SUM(AR49:AR53) -> 0 | AS55: =SUM(AG55:AR55) -> 0 | AU55: =SUM(AU49:AU53) -> 0 | AV55: =SUM(AV49:AV53) -> 0 | AW55: =SUM(AW49:AW53) -> 0 | AX55: =SUM(AX49:AX53) -> 0 | AY55: =SUM(AY49:AY53) -> 0 | AZ55: =SUM(AZ49:AZ53) -> 0 | BA55: =SUM(BA49:BA53) -> 0 | BB55: =SUM(BB49:BB53) -> 0 | ... BF55: =SUM(BF49:BF53) -> 0 | BG55: =SUM(AU55:BF55) -> 0

Sheet BUDGET TRACKING
A1: BUDGET TRACKING
C11: Date | D11: Type | E11: Category | F11: Amount | G11: Details | H11: BALANCE | I11: EFFECTIVE DATE
C12: 37266 | D12: INCOME | E12: DIVIDENDS | F12: 150 | H12: {=SUMPRODUCT(TRACKING[Amount],(TRACKING[Date]<=TRACKING[[#This Row],[Date]])*1)} -> 150 | I12: =IF(AND(TRACKING[[#This Row],[Type]]="INCOME",shift_late_income_status_2="Active",DAY(TRACKING[[#This Row],[Date]])>=Shift_late_income_starting_day), DATE(YEAR(TRACKING[[#This Row],[Date]]),MONTH(TRACKING[[#This Row],[Date]])+1,1),TRACKING[[#This Row],[Date]]) -> 37266
C13: 37295 | D13: EXPENSES | E13: TRANSPORTATION | F13: 100 | H13: {=SUMPRODUCT(TRACKING[Amount],(TRACKING[Date]<=TRACKING[[#This Row],[Date]])*1)} -> 250 | I13: =IF(AND(TRACKING[[#This Row],[Type]]="INCOME",shift_late_income_status_2="Active",DAY(TRACKING[[#This Row],[Date]])>=Shift_late_income_starting_day), DATE(YEAR(TRACKING[[#This Row],[Date]]),MONTH(TRACKING[[#This Row],[Date]])+1,1),TRACKING[[#This Row],[Date]]) -> 37295
C14: 44562 | D14: INCOME | E14: Employment (NET) | F14: 3500 | H14: {=SUMPRODUCT(TRACKING[Amount],(TRACKING[Date]<=TRACKING[[#This Row],[Date]])*1)} -> 3750 | I14: =IF(AND(TRACKING[[#This Row],[Type]]="INCOME",shift_late_income_status_2="Active",DAY(TRACKING[[#This Row],[Date]])>=Shift_late_income_starting_day), DATE(YEAR(TRACKING[[#This Row],[Date]]),MONTH(TRACKING[[#This Row],[Date]])+1,1),TRACKING[[#This Row],[Date]]) -> 44562
C15: 44563 | D15: EXPENSES | E15: HOUSING | F15: 1200 | H15: {=SUMPRODUCT(TRACKING[Amount],(TRACKING[Date]<=TRACKING[[#This Row],[Date]])*1)} -> 4950 | I15: =IF(AND(TRACKING[[#This Row],[Type]]="INCOME",shift_late_income_status_2="Active",DAY(TRACKING[[#This Row],[Date]])>=Shift_late_income_starting_day), DATE(YEAR(TRACKING[[#This Row],[Date]]),MONTH(TRACKING[[#This Row],[Date]])+1,1),TRACKING[[#This Row],[Date]]) -> 44563
C16: 44565 | D16: SAVINGS | E16: EMERGENCY FUND | F16: 1000 | H16: {=SUMPRODUCT(TRACKING[Amount],(TRACKING[Date]<=TRACKING[[#This Row],[Date]])*1)} -> 5950 | I16: =IF(AND(TRACKING[[#This Row],[Type]]="INCOME",shift_late_income_status_2="Active",DAY(TRACKING[[#This Row],[Date]])>=Shift_late_income_starting_day), DATE(YEAR(TRACKING[[#This Row],[Date]]),MONTH(TRACKING[[#This Row],[Date]])+1,1),TRACKING[[#This Row],[Date]]) -> 44565
C17: 44568 | D17: EXPENSES | E17: GROCERIES | F17: 120 | H17: {=SUMPRODUCT(TRACKING[Amount],(TRACKING[Date]<=TRACKING[[#This Row],[Date]])*1)} -> 6070 | I17: =IF(AND(TRACKING[[#This Row],[Type]]="INCOME",shift_late_income_status_2="Active",DAY(TRACKING[[#This Row],[Date]])>=Shift_late_income_starting_day), DATE(YEAR(TRACKING[[#This Row],[Date]]),MONTH(TRACKING[[#This Row],[Date]])+1,1),TRACKING[[#This Row],[Date]]) -> 44568
C18: 44570 | D18: EXPENSES | E18: TRANSPORTATION | F18: 80 | H18: {=SUMPRODUCT(TRACKING[Amount],(TRACKING[Date]<=TRACKING[[#This Row],[Date]])*1)} -> 6150 | I18: =IF(AND(TRACKING[[#This Row],[Type]]="INCOME",shift_late_income_status_2="Active",DAY(TRACKING[[#This Row],[Date]])>=Shift_late_income_starting_day), DATE(YEAR(TRACKING[[#This Row],[Date]]),MONTH(TRACKING[[#This Row],[Date]])+1,1),TRACKING[[#This Row],[Date]]) -> 44570
C19: 44571 | D19: EXPENSES | E19: FUN & VACATION | F19: 120 | H19: {=SUMPRODUCT(TRACKING[Amount],(TRACKING[Date]<=TRACKING[[#This Row],[Date]])*1)} -> 6270 | I19: =IF(AND(TRACKING[[#This Row],[Type]]="INCOME",shift_late_income_status_2="Active",DAY(TRACKING[[#This Row],[Date]])>=Shift_late_income_starting_day), DATE(YEAR(TRACKING[[#This Row],[Date]]),MONTH(TRACKING[[#This Row],[Date]])+1,1),TRACKING[[#This Row],[Date]]) -> 44571
C20: 44573 | D20: EXPENSES | E20: MEDIA | F20: 50 | H20: {=SUMPRODUCT(TRACKING[Amount],(TRACKING[Date]<=TRACKING[[#This Row],[Date]])*1)} -> 6320 | I20: =IF(AND(TRACKING[[#This Row],[Type]]="INCOME",shift_late_income_status_2="Active",DAY(TRACKING[[#This Row],[Date]])>=Shift_late_income_starting_day), DATE(YEAR(TRACKING[[#This Row],[Date]]),MONTH(TRACKING[[#This Row],[Date]])+1,1),TRACKING[[#This Row],[Date]]) -> 44573
C21: 44574 | D21: EXPENSES | E21: BODY CARE & MEDICINE | F21: 70 | H21: {=SUMPRODUCT(TRACKING[Amount],(TRACKING[Date]<=TRACKING[[#This Row],[Date]])*1)} -> 6390 | I21: =IF(AND(TRACKING[[#This Row],[Type]]="INCOME",shift_late_income_status_2="Active",DAY(TRACKING[[#This Row],[Date]])>=Shift_late_income_starting_day), DATE(YEAR(TRACKING[[#This Row],[Date]]),MONTH(TRACKING[[#This Row],[Date]])+1,1),TRACKING[[#This Row],[Date]]) -> 44574
C22: 44575 | D22: EXPENSES | E22: GROCERIES | F22: 80 | H22: {=SUMPRODUCT(TRACKING[Amount],(TRACKING[Date]<=TRACKING[[#This Row],[Date]])*1)} -> 6470 | I22: =IF(AND(TRACKING[[#This Row],[Type]]="INCOME",shift_late_income_status_2="Active",DAY(TRACKING[[#This Row],[Date]])>=Shift_late_income_starting_day), DATE(YEAR(TRACKING[[#This Row],[Date]]),MONTH(TRACKING[[#This Row],[Date]])+1,1),TRACKING[[#This Row],[Date]]) -> 44575
C23: 44576 | D23: INCOME | E23: SIDE HUSTLE(NET) | F23: 1200 | H23: {=SUMPRODUCT(TRACKING[Amount],(TRACKING[Date]<=TRACKING[[#This Row],[Date]])*1)} -> 7670 | I23: =IF(AND(TRACKING[[#This Row],[Type]]="INCOME",shift_late_income_status_2="Active",DAY(TRACKING[[#This Row],[Date]])>=Shift_late_income_starting_day), DATE(YEAR(TRACKING[[#This Row],[Date]]),MONTH(TRACKING[[#This Row],[Date]])+1,1),TRACKING[[#This Row],[Date]]) -> 44576
... C69: 44635 | D69: INCOME | E69: SIDE HUSTLE(NET) | F69: 1100 | H69: {=SUMPRODUCT(TRACKING[Amount],(TRACKING[Date]<=TRACKING[[#This Row],[Date]])*1)} -> 24280 | I69: =IF(AND(TRACKING[[#This Row],[Type]]="INCOME",shift_late_income_status_2="Active",DAY(TRACKING[[#This Row],[Date]])>=Shift_late_income_starting_day), DATE(YEAR(TRACKING[[#This Row],[Date]]),MONTH(TRACKING[[#This Row],[Date]])+1,1),TRACKING[[#This Row],[Date]]) -> 44635

Sheet BUDGET DASHBOARD
A1: BUDGET DASHBOARD
Y11: =STARTING_YEAR -> 2022 | AF11: ="SUMMARY -"&IF(selected_period="Total Year",selected_year & "(Total Year)",selected_period_display & " " & selected_year) -> SUMMARY -March 0
C12: row_id | D12: header_row_id | E12: is_header | F12: is_cat | G12: is_total | H12: is_empty | I12: type | J12: item | K12: tracked | L12: budget | M12: sort_min_row | N12: sort_max_row | O12: tracked_range | P12: tracked_rank | Q12: budget_range | R12: budget_rank | S12: comb_rank | T12: comb_rank_range | U12: comb_rank_norm | V12: comb_rank_norm_run_range | W12: comb_rank_unique | X12: sorted_row_id[Lookup]
C13: {=INCOME_HEADER_ROW} -> 9 | D13: 9 | E13: 1 | F13: 0 | G13: 0 | H13: 0 | I13: INCOME | J13: {=IFERROR(INDEX('BUDGET PLANNING'!$C:$C,row_id),"")} -> INCOME | M13: {=IF(is_cat,IF(header_row_id=INCOME_HEADER_ROW,MATCH(INCOME_MIN_ROW,$C:$C,0),""),"")} | O13: =IF(is_cat,ADDRESS(sort_min_row,COLUMN(tracked))&":"&ADDRESS(sort_max_row,COLUMN(tracked)),"") | P13: =IF(is_cat,RANK(tracked,INDIRECT(tracked_range),0),"") | Q13: =IF(is_cat,ADDRESS(sort_min_row,COLUMN(budget))&":"&ADDRESS(sort_max_row,COLUMN(budget)),"") | R13: =IF(is_cat,RANK(budget,INDIRECT(budget_range),0),"") | S13: =IF(is_cat,_xlfn.NUMBERVALUE(tracked_rank & budget_rank),"") | T13: =IF(is_cat,ADDRESS(sort_min_row,COLUMN(comb_rank)) & ":" & ADDRESS(sort_max_row,COLUMN(comb_rank)),"") | U13: =IF(is_cat,RANK(comb_rank,INDIRECT(comb_rank_range),1),"") | V13: =IF(is_cat,ADDRESS(sort_min_row,COLUMN(comb_rank_norm))& ":" & ADDRESS(ROW(),COLUMN(comb_rank_norm)),"") | W13: =IF(is_cat,comb_rank_norm+COUNTIF(INDIRECT(comb_rank_norm_run_range),comb_rank_norm)-1,"") | X13: =IF(is_cat,header_row_id+comb_rank_unique,row_id) -> 9 | Y13: =IF(is_empty,"",INDEX($J:$J,MATCH(row_id,$X:$X,0))) -> INCOME | Z13: =IF(is_empty,"",IF(is_header,"TRACKED",INDEX($K:$K,MATCH(row_id,$X:$X,0)))) -> TRACKED | AA13: =IF(is_empty,"",IF(is_header,"BUDGET",INDEX($L:$L,MATCH(row_id,$X:$X,0)))) -> BUDGET | AB13: =IF(is_empty,"",IF(is_header,"%Compl.",IFERROR(out_tracked/out_budget,"-"))) -> %Compl. | AC13: =IF(is_empty,"",IF(is_header,"Remaining",IF(out_budget-out_tracked>0,out_budget-out_tracked,0))) -> Remaining | AD13: =IF(is_empty,"",IF(is_header,"Excess",IF(out_budget-out_tracked<0,out_tracked-out_budget,0))) -> Excess
C14: =C13+1 -> 10 | D14: 9 | E14: 0 | F14: 1 | G14: 0 | H14: 0 | I14: INCOME | J14: {=IFERROR(INDEX('BUDGET PLANNING'!$C:$C,row_id),"")} -> EMPLOYMENT(NET) | K14: 3500 | L14: 51000 | M14: 14 | N14: 16 | O14: =IF(is_cat,ADDRESS(sort_min_row,COLUMN(tracked))&":"&ADDRESS(sort_max_row,COLUMN(tracked)),"") -> $K$14:$K$16 | P14: =IF(is_cat,RANK(tracked,INDIRECT(tracked_range),0),"") -> 1 | Q14: =IF(is_cat,ADDRESS(sort_min_row,COLUMN(budget))&":"&ADDRESS(sort_max_row,COLUMN(budget)),"") -> $L$14:$L$16 | R14: =IF(is_cat,RANK(budget,INDIRECT(budget_range),0),"") -> 1 | S14: =IF(is_cat,_xlfn.NUMBERVALUE(tracked_rank & budget_rank),"") -> 11 | T14: =IF(is_cat,ADDRESS(sort_min_row,COLUMN(comb_rank)) & ":" & ADDRESS(sort_max_row,COLUMN(comb_rank)),"") -> $S$14:$S$16 | U14: =IF(is_cat,RANK(comb_rank,INDIRECT(comb_rank_range),1),"") -> 1 | V14: =IF(is_cat,ADDRESS(sort_min_row,COLUMN(comb_rank_norm))& ":" & ADDRESS(ROW(),COLUMN(comb_rank_norm)),"") -> $U$14:$U$14 | W14: =IF(is_cat,comb_rank_norm+COUNTIF(INDIRECT(comb_rank_norm_run_range),comb_rank_norm)-1,"") -> 1 | X14: =IF(is_cat,header_row_id+comb_rank_unique,row_id) -> 10 | Y14: =IF(is_empty,"",INDEX($J:$J,MATCH(row_id,$X:$X,0))) -> EMPLOYMENT(NET) | Z14: =IF(is_empty,"",IF(is_header,"TRACKED",INDEX($K:$K,MATCH(row_id,$X:$X,0)))) -> 3500 | AA14: =IF(is_empty,"",IF(is_header,"BUDGET",INDEX($L:$L,MATCH(row_id,$X:$X,0)))) -> 51000 | AB14: =IF(is_empty,"",IF(is_header,"%Compl.",IFERROR(out_tracked/out_budget,"-"))) -> 0.068627451 | AC14: =IF(is_empty,"",IF(is_header,"Remaining",IF(out_budget-out_tracked>0,out_budget-out_tracked,0))) -> 47500 | AD14: =IF(is_empty,"",IF(is_header,"Excess",IF(out_budget-out_tracked<0,out_tracked-out_budget,0))) -> 0
C15: =C14+1 -> 11 | D15: 9 | E15: 0 | F15: 1 | G15: 0 | H15: 0 | I15: INCOME | J15: SIDE HUSTLE(NET) | K15: 500 | L15: 12000 | M15: 14 | N15: 16 | O15: =IF(is_cat,ADDRESS(sort_min_row,COLUMN(tracked))&":"&ADDRESS(sort_max_row,COLUMN(tracked)),"") -> $K$14:$K$16 | P15: =IF(is_cat,RANK(tracked,INDIRECT(tracked_range),0),"") -> 2 | Q15: =IF(is_cat,ADDRESS(sort_min_row,COLUMN(budget))&":"&ADDRESS(sort_max_row,COLUMN(budget)),"") -> $L$14:$L$16 | R15: =IF(is_cat,RANK(budget,INDIRECT(budget_range),0),"") -> 2 | S15: =IF(is_cat,_xlfn.NUMBERVALUE(tracked_rank & budget_rank),"") -> 22 | T15: =IF(is_cat,ADDRESS(sort_min_row,COLUMN(comb_rank)) & ":" & ADDRESS(sort_max_row,COLUMN(comb_rank)),"") -> $S$14:$S$16 | U15: =IF(is_cat,RANK(comb_rank,INDIRECT(comb_rank_range),1),"") -> 2 | V15: =IF(is_cat,ADDRESS(sort_min_row,COLUMN(comb_rank_norm))& ":" & ADDRESS(ROW(),COLUMN(comb_rank_norm)),"") -> $U$14:$U$15 | W15: =IF(is_cat,comb_rank_norm+COUNTIF(INDIRECT(comb_rank_norm_run_range),comb_rank_norm)-1,"") -> 2 | X15: =IF(is_cat,header_row_id+comb_rank_unique,row_id) -> 11 | Y15: =IF(is_empty,"",INDEX($J:$J,MATCH(row_id,$X:$X,0))) -> SIDE HUSTLE(NET) | Z15: =IF(is_empty,"",IF(is_header,"TRACKED",INDEX($K:$K,MATCH(row_id,$X:$X,0)))) -> 500 | AA15: =IF(is_empty,"",IF(is_header,"BUDGET",INDEX($L:$L,MATCH(row_id,$X:$X,0)))) -> 12000 | AB15: =IF(is_empty,"",IF(is_header,"%Compl.",IFERROR(out_tracked/out_budget,"-"))) -> 0.041666667 | AC15: =IF(is_empty,"",IF(is_header,"Remaining",IF(out_budget-out_tracked>0,out_budget-out_tracked,0))) -> 11500 | AD15: =IF(is_empty,"",IF(is_header,"Excess",IF(out_budget-out_tracked<0,out_tracked-out_budget,0))) -> 0
C16: =C15+1 -> 12 | D16: 9 | E16: 0 | F16: 1 | G16: 0 | H16: 0 | I16: INCOME | J16: DIVIDENDS | K16: - | L16: 1200 | M16: 14 | N16: 16 | O16: =IF(is_cat,ADDRESS(sort_min_row,COLUMN(tracked))&":"&ADDRESS(sort_max_row,COLUMN(tracked)),"") -> $K$14:$K$16 | P16: 3 | Q16: =IF(is_cat,ADDRESS(sort_min_row,COLUMN(budget))&":"&ADDRESS(sort_max_row,COLUMN(budget)),"") -> $L$14:$L$16 | R16: =IF(is_cat,RANK(budget,INDIRECT(budget_range),0),"") -> 3 | S16: =IF(is_cat,_xlfn.NUMBERVALUE(tracked_rank & budget_rank),"") -> 33 | T16: =IF(is_cat,ADDRESS(sort_min_row,COLUMN(comb_rank)) & ":" & ADDRESS(sort_max_row,COLUMN(comb_rank)),"") -> $S$14:$S$16 | U16: =IF(is_cat,RANK(comb_rank,INDIRECT(comb_rank_range),1),"") -> 3 | V16: =IF(is_cat,ADDRESS(sort_min_row,COLUMN(comb_rank_norm))& ":" & ADDRESS(ROW(),COLUMN(comb_rank_norm)),"") -> $U$14:$U$16 | W16: =IF(is_cat,comb_rank_norm+COUNTIF(INDIRECT(comb_rank_norm_run_range),comb_rank_norm)-1,"") -> 3 | X16: =IF(is_cat,header_row_id+comb_rank_unique,row_id) -> 12 | Y16: =IF(is_empty,"",INDEX($J:$J,MATCH(row_id,$X:$X,0))) -> DIVIDENDS | Z16: 50 | AA16: =IF(is_empty,"",IF(is_header,"BUDGET",INDEX($L:$L,MATCH(row_id,$X:$X,0)))) -> 1200 | AB16: 0 | AC16: 1200 | AD16: 0
C17: 20 | D17: 9 | E17: 0 | F17: 0 | G17: 1 | H17: 0 | I17: INCOME | J17: TOTAL | K17: =SUM(K14:K15) -> 4000 | L17: =SUM(L14:L16) -> 64200 | M17: {=IF(is_cat,IF(header_row_id=INCOME_HEADER_ROW,MATCH(INCOME_MIN_ROW,$C:$C,0),""),"")} | O17: =IF(is_cat,ADDRESS(sort_min_row,COLUMN(tracked))&":"&ADDRESS(sort_max_row,COLUMN(tracked)),"") | P17: =IF(is_cat,RANK(tracked,INDIRECT(tracked_range),0),"") | Q17: =IF(is_cat,ADDRESS(sort_min_row,COLUMN(budget))&":"&ADDRESS(sort_max_row,COLUMN(budget)),"") | R17: =IF(is_cat,RANK(budget,INDIRECT(budget_range),0),"") | S17: =IF(is_cat,_xlfn.NUMBERVALUE(tracked_rank & budget_rank),"") | T17: =IF(is_cat,ADDRESS(sort_min_row,COLUMN(comb_rank)) & ":" & ADDRESS(sort_max_row,COLUMN(comb_rank)),"") | U17: =IF(is_cat,RANK(comb_rank,INDIRECT(comb_rank_range),1),"") | V17: =IF(is_cat,ADDRESS(sort_min_row,COLUMN(comb_rank_norm))& ":" & ADDRESS(ROW(),COLUMN(comb_rank_norm)),"") | W17: =IF(is_cat,comb_rank_norm+COUNTIF(INDIRECT(comb_rank_norm_run_range),comb_rank_norm)-1,"") | X17: =IF(is_cat,header_row_id+comb_rank_unique,row_id) -> 20 | Y17: =IF(is_empty,"",INDEX($J:$J,MATCH(row_id,$X:$X,0))) -> TOTAL | Z17: =SUM(Z14:Z16) -> 4050 | AA17: =IF(is_empty,"",IF(is_header,"BUDGET",INDEX($L:$L,MATCH(row_id,$X:$X,0)))) -> 64200 | AB17: =IF(is_empty,"",IF(is_header,"%Compl.",IFERROR(out_tracked/out_budget,"-"))) -> 0.063084112 | AC17: =IF(is_empty,"",IF(is_header,"Remaining",IF(out_budget-out_tracked>0,out_budget-out_tracked,0))) -> 60150 | AD17: =IF(is_empty,"",IF(is_header,"Excess",IF(out_budget-out_tracked<0,out_tracked-out_budget,0))) -> 0 | AI17: =CALCULATIONS!E35 -> Employment(Net) | AJ17: =CALCULATIONS!F35 -> 3500
D18: -1 | F18: 0 | H18: 1 | M18: {=IF(is_cat,IF(header_row_id=INCOME_HEADER_ROW,MATCH(INCOME_MIN_ROW,$C:$C,0),""),"")} | O18: =IF(is_cat,ADDRESS(sort_min_row,COLUMN(tracked))&":"&ADDRESS(sort_max_row,COLUMN(tracked)),"") | P18: =IF(is_cat,RANK(tracked,INDIRECT(tracked_range),0),"") | Q18: =IF(is_cat,ADDRESS(sort_min_row,COLUMN(budget))&":"&ADDRESS(sort_max_row,COLUMN(budget)),"") | R18: =IF(is_cat,RANK(budget,INDIRECT(budget_range),0),"") | S18: =IF(is_cat,_xlfn.NUMBERVALUE(tracked_rank & budget_rank),"") | T18: =IF(is_cat,ADDRESS(sort_min_row,COLUMN(comb_rank)) & ":" & ADDRESS(sort_max_row,COLUMN(comb_rank)),"") | U18: =IF(is_cat,RANK(comb_rank,INDIRECT(comb_rank_range),1),"") | V18: =IF(is_cat,ADDRESS(sort_min_row,COLUMN(comb_rank_norm))& ":" & ADDRESS(ROW(),COLUMN(comb_rank_norm)),"") | W18: =IF(is_cat,comb_rank_norm+COUNTIF(INDIRECT(comb_rank_norm_run_range),comb_rank_norm)-1,"") | X18: =IF(is_cat,header_row_id+comb_rank_unique,row_id) -> 0 | Y18: =IF(is_empty,"",INDEX($J:$J,MATCH(row_id,$X:$X,0))) | Z18: =IF(is_empty,"",IF(is_header,"TRACKED",INDEX($K:$K,MATCH(row_id,$X:$X,0)))) | AA18: =IF(is_empty,"",IF(is_header,"BUDGET",INDEX($L:$L,MATCH(row_id,$X:$X,0)))) | AB18: =IF(is_empty,"",IF(is_header,"%Compl.",IFERROR(out_tracked/out_budget,"-"))) | AC18: =IF(is_empty,"",IF(is_header,"Remaining",IF(out_budget-out_tracked>0,out_budget-out_tracked,0))) | AD18: =IF(is_empty,"",IF(is_header,"Excess",IF(out_budget-out_tracked<0,out_tracked-out_budget,0))) | AI18: =CALCULATIONS!E36 -> Side Hustle(Net) | AJ18: =CALCULATIONS!F36 -> 500
C19: 22 | D19: 22 | E19: 1 | F19: 0 | G19: 0 | H19: 0 | I19: EXPENSES | J19: EXPENSES | O19: =IF(is_cat,ADDRESS(sort_min_row,COLUMN(tracked))&":"&ADDRESS(sort_max_row,COLUMN(tracked)),"") | P19: =IF(is_cat,RANK(tracked,INDIRECT(tracked_range),0),"") | Q19: =IF(is_cat,ADDRESS(sort_min_row,COLUMN(budget))&":"&ADDRESS(sort_max_row,COLUMN(budget)),"") | R19: =IF(is_cat,RANK(budget,INDIRECT(budget_range),0),"") | S19: =IF(is_cat,_xlfn.NUMBERVALUE(tracked_rank & budget_rank),"") | T19: =IF(is_cat,ADDRESS(sort_min_row,COLUMN(comb_rank)) & ":" & ADDRESS(sort_max_row,COLUMN(comb_rank)),"") | U19: =IF(is_cat,RANK(comb_rank,INDIRECT(comb_rank_range),1),"") | V19: =IF(is_cat,ADDRESS(sort_min_row,COLUMN(comb_rank_norm))& ":" & ADDRESS(ROW(),COLUMN(comb_rank_norm)),"") | W19: =IF(is_cat,comb_rank_norm+COUNTIF(INDIRECT(comb_rank_norm_run_range),comb_rank_norm)-1,"") | X19: =IF(is_cat,header_row_id+comb_rank_unique,row_id) -> 22 | Y19: =IF(is_empty,"",INDEX($J:$J,MATCH(row_id,$X:$X,0))) -> EXPENSES | Z19: =IF(is_empty,"",IF(is_header,"TRACKED",INDEX($K:$K,MATCH(row_id,$X:$X,0)))) -> TRACKED | AA19: =IF(is_empty,"",IF(is_header,"BUDGET",INDEX($L:$L,MATCH(row_id,$X:$X,0)))) -> BUDGET | AB19: =IF(is_empty,"",IF(is_header,"%Compl.",IFERROR(out_tracked/out_budget,"-"))) -> %Compl. | AC19: =IF(is_empty,"",IF(is_header,"Remaining",IF(out_budget-out_tracked>0,out_budget-out_tracked,0))) -> Remaining | AD19: =IF(is_empty,"",IF(is_header,"Excess",IF(out_budget-out_tracked<0,out_tracked-out_budget,0))) -> Excess | AI19: =CALCULATIONS!E37 -> Dividends | AJ19: =CALCULATIONS!F37 -> 50
C20: =C19+1 -> 23 | D20: 22 | E20: 0 | F20: 1 | G20: 0 | H20: 0 | I20: EXPENSES | J20: HOUSING | K20: 1200 | L20: 14400 | M20: 20 | N20: 28 | O20: =IF(is_cat,ADDRESS(sort_min_row,COLUMN(tracked))&":"&ADDRESS(sort_max_row,COLUMN(tracked)),"") -> $K$20:$K$28 | P20: =IF(is_cat,RANK(tracked,INDIRECT(tracked_range),0),"") -> 1 | Q20: =IF(is_cat,ADDRESS(sort_min_row,COLUMN(budget))&":"&ADDRESS(sort_max_row,COLUMN(budget)),"") -> $L$20:$L$28 | R20: =IF(is_cat,RANK(budget,INDIRECT(budget_range),0),"") -> 1 | S20: =IF(is_cat,_xlfn.NUMBERVALUE(tracked_rank & budget_rank),"") -> 11 | T20: =IF(is_cat,ADDRESS(sort_min_row,COLUMN(comb_rank)) & ":" & ADDRESS(sort_max_row,COLUMN(comb_rank)),"") -> $S$20:$S$28 | U20: =IF(is_cat,RANK(comb_rank,INDIRECT(comb_rank_range),1),"") -> 1 | V20: =IF(is_cat,ADDRESS(sort_min_row,COLUMN(comb_rank_norm))& ":" & ADDRESS(ROW(),COLUMN(comb_rank_norm)),"") -> $U$20:$U$20 | W20: =IF(is_cat,comb_rank_norm+COUNTIF(INDIRECT(comb_rank_norm_run_range),comb_rank_norm)-1,"") -> 1 | X20: =IF(is_cat,header_row_id+comb_rank_unique,row_id) -> 23 | Y20: =IF(is_empty,"",INDEX($J:$J,MATCH(row_id,$X:$X,0))) -> HOUSING | Z20: =IF(is_empty,"",IF(is_header,"TRACKED",INDEX($K:$K,MATCH(row_id,$X:$X,0)))) -> 1200 | AA20: =IF(is_empty,"",IF(is_header,"BUDGET",INDEX($L:$L,MATCH(row_id,$X:$X,0)))) -> 14400 | AB20: =IF(is_empty,"",IF(is_header,"%Compl.",IFERROR(out_tracked/out_budget,"-"))) -> 0.083333333 | AC20: =IF(is_empty,"",IF(is_header,"Remaining",IF(out_budget-out_tracked>0,out_budget-out_tracked,0))) -> 13200 | AD20: =IF(is_empty,"",IF(is_header,"Excess",IF(out_budget-out_tracked<0,out_tracked-out_budget,0))) -> 0
C21: =C20+1 -> 24 | D21: 22 | E21: 0 | F21: 1 | G21: 0 | H21: 0 | I21: EXPENSES | J21: UTILITIES | K21: - | L21: 3600 | M21: 20 | N21: 28 | O21: =IF(is_cat,ADDRESS(sort_min_row,COLUMN(tracked))&":"&ADDRESS(sort_max_row,COLUMN(tracked)),"") -> $K$20:$K$28 | P21: 5 | Q21: =IF(is_cat,ADDRESS(sort_min_row,COLUMN(budget))&":"&ADDRESS(sort_max_row,COLUMN(budget)),"") -> $L$20:$L$28 | R21: =IF(is_cat,RANK(budget,INDIRECT(budget_range),0),"") -> 4 | S21: =IF(is_cat,_xlfn.NUMBERVALUE(tracked_rank & budget_rank),"") -> 54 | T21: =IF(is_cat,ADDRESS(sort_min_row,COLUMN(comb_rank)) & ":" & ADDRESS(sort_max_row,COLUMN(comb_rank)),"") -> $S$20:$S$28 | U21: =IF(is_cat,RANK(comb_rank,INDIRECT(comb_rank_range),1),"") -> 6 | V21: =IF(is_cat,ADDRESS(sort_min_row,COLUMN(comb_rank_norm))& ":" & ADDRESS(ROW(),COLUMN(comb_rank_norm)),"") -> $U$20:$U$21 | W21: =IF(is_cat,comb_rank_norm+COUNTIF(INDIRECT(comb_rank_norm_run_range),comb_rank_norm)-1,"") -> 6 | X21: =IF(is_cat,header_row_id+comb_rank_unique,row_id) -> 28 | Y21: =IF(is_empty,"",INDEX($J:$J,MATCH(row_id,$X:$X,0))) -> GROCERIES | Z21: 400 | AA21: =IF(is_empty,"",IF(is_header,"BUDGET",INDEX($L:$L,MATCH(row_id,$X:$X,0)))) -> 4200 | AB21: =IF(is_empty,"",IF(is_header,"%Compl.",IFERROR(out_tracked/out_budget,"-"))) -> 0.095238095 | AC21: =IF(is_empty,"",IF(is_header,"Remaining",IF(out_budget-out_tracked>0,out_budget-out_tracked,0))) -> 3800 | AD21: =IF(is_empty,"",IF(is_header,"Excess",IF(out_budget-out_tracked<0,out_tracked-out_budget,0))) -> 0
C22: =C21+1 -> 25 | D22: 22 | E22: 0 | F22: 1 | G22: 0 | H22: 0 | I22: EXPENSES | J22: GROCERIES | K22: 200 | L22: 4200 | M22: 20 | N22: 28 | O22: =IF(is_cat,ADDRESS(sort_min_row,COLUMN(tracked))&":"&ADDRESS(sort_max_row,COLUMN(tracked)),"") -> $K$20:$K$28 | P22: =IF(is_cat,RANK(tracked,INDIRECT(tracked_range),0),"") -> 2 | Q22: =IF(is_cat,ADDRESS(sort_min_row,COLUMN(budget))&":"&ADDRESS(sort_max_row,COLUMN(budget)),"") -> $L$20:$L$28 | R22: =IF(is_cat,RANK(budget,INDIRECT(budget_range),0),"") -> 3 | S22: =IF(is_cat,_xlfn.NUMBERVALUE(tracked_rank & budget_rank),"") -> 23 | T22: =IF(is_cat,ADDRESS(sort_min_row,COLUMN(comb_rank)) & ":" & ADDRESS(sort_max_row,COLUMN(comb_rank)),"") -> $S$20:$S$28 | U22: =IF(is_cat,RANK(comb_rank,INDIRECT(comb_rank_range),1),"") -> 2 | V22: =IF(is_cat,ADDRESS(sort_min_row,COLUMN(comb_rank_norm))& ":" & ADDRESS(ROW(),COLUMN(comb_rank_norm)),"") -> $U$20:$U$22 | W22: =IF(is_cat,comb_rank_norm+COUNTIF(INDIRECT(comb_rank_norm_run_range),comb_rank_norm)-1,"") -> 2 | X22: =IF(is_cat,header_row_id+comb_rank_unique,row_id) -> 24 | Y22: =IF(is_empty,"",INDEX($J:$J,MATCH(row_id,$X:$X,0))) -> CLOTHING | Z22: 140 | AA22: =IF(is_empty,"",IF(is_header,"BUDGET",INDEX($L:$L,MATCH(row_id,$X:$X,0)))) -> 2400 | AB22: =IF(is_empty,"",IF(is_header,"%Compl.",IFERROR(out_tracked/out_budget,"-"))) -> 0.058333333 | AC22: =IF(is_empty,"",IF(is_header,"Remaining",IF(out_budget-out_tracked>0,out_budget-out_tracked,0))) -> 2260 | AD22: =IF(is_empty,"",IF(is_header,"Excess",IF(out_budget-out_tracked<0,out_tracked-out_budget,0))) -> 0
C23: =C22+1 -> 26 | D23: 22 | E23: 0 | F23: 1 | G23: 0 | H23: 0 | I23: EXPENSES | J23: TRANSPORTATION | K23: 100 | L23: 3600 | M23: 20 | N23: 28 | O23: =IF(is_cat,ADDRESS(sort_min_row,COLUMN(tracked))&":"&ADDRESS(sort_max_row,COLUMN(tracked)),"") -> $K$20:$K$28 | P23: =IF(is_cat,RANK(tracked,INDIRECT(tracked_range),0),"") -> 4 | Q23: =IF(is_cat,ADDRESS(sort_min_row,COLUMN(budget))&":"&ADDRESS(sort_max_row,COLUMN(budget)),"") -> $L$20:$L$28 | R23: =IF(is_cat,RANK(budget,INDIRECT(budget_range),0),"") -> 4 | S23: =IF(is_cat,_xlfn.NUMBERVALUE(tracked_rank & budget_rank),"") -> 44 | T23: =IF(is_cat,ADDRESS(sort_min_row,COLUMN(comb_rank)) & ":" & ADDRESS(sort_max_row,COLUMN(comb_rank)),"") -> $S$20:$S$28 | U23: =IF(is_cat,RANK(comb_rank,INDIRECT(comb_rank_range),1),"") -> 4 | V23: =IF(is_cat,ADDRESS(sort_min_row,COLUMN(comb_rank_norm))& ":" & ADDRESS(ROW(),COLUMN(comb_rank_norm)),"") -> $U$20:$U$23 | W23: =IF(is_cat,comb_rank_norm+COUNTIF(INDIRECT(comb_rank_norm_run_range),comb_rank_norm)-1,"") -> 4 | X23: =IF(is_cat,header_row_id+comb_rank_unique,row_id) -> 26 | Y23: =IF(is_empty,"",INDEX($J:$J,MATCH(row_id,$X:$X,0))) -> TRANSPORTATION | Z23: 380 | AA23: =IF(is_empty,"",IF(is_header,"BUDGET",INDEX($L:$L,MATCH(row_id,$X:$X,0)))) -> 3600 | AB23: =IF(is_empty,"",IF(is_header,"%Compl.",IFERROR(out_tracked/out_budget,"-"))) -> 0.10555556 | AC23: =IF(is_empty,"",IF(is_header,"Remaining",IF(out_budget-out_tracked>0,out_budget-out_tracked,0))) -> 3220 | AD23: =IF(is_empty,"",IF(is_header,"Excess",IF(out_budget-out_tracked<0,out_tracked-out_budget,0))) -> 0 | AI23: =CALCULATIONS!E41 -> TOTAL | AJ23: =CALCULATIONS!F41 -> 4050
C24: =C23+1 -> 27 | D24: 22 | E24: 0 | F24: 1 | G24: 0 | H24: 0 | I24: EXPENSES | J24: INSURANCES | K24: - | L24: 600 | M24: 20 | N24: 28 | O24: =IF(is_cat,ADDRESS(sort_min_row,COLUMN(tracked))&":"&ADDRESS(sort_max_row,COLUMN(tracked)),"") -> $K$20:$K$28 | P24: 5 | Q24: =IF(is_cat,ADDRESS(sort_min_row,COLUMN(budget))&":"&ADDRESS(sort_max_row,COLUMN(budget)),"") -> $L$20:$L$28 | R24: =IF(is_cat,RANK(budget,INDIRECT(budget_range),0),"") -> 8 | S24: =IF(is_cat,_xlfn.NUMBERVALUE(tracked_rank & budget_rank),"") -> 58 | T24: =IF(is_cat,ADDRESS(sort_min_row,COLUMN(comb_rank)) & ":" & ADDRESS(sort_max_row,COLUMN(comb_rank)),"") -> $S$20:$S$28 | U24: =IF(is_cat,RANK(comb_rank,INDIRECT(comb_rank_range),1),"") -> 8 | V24: =IF(is_cat,ADDRESS(sort_min_row,COLUMN(comb_rank_norm))& ":" & ADDRESS(ROW(),COLUMN(comb_rank_norm)),"") -> $U$20:$U$24 | W24: =IF(is_cat,comb_rank_norm+COUNTIF(INDIRECT(comb_rank_norm_run_range),comb_rank_norm)-1,"") -> 8 | X24: =IF(is_cat,header_row_id+comb_rank_unique,row_id) -> 30 | Y24: =IF(is_empty,"",INDEX($J:$J,MATCH(row_id,$X:$X,0))) -> FUN & VACATION | Z24: 250 | AA24: =IF(is_empty,"",IF(is_header,"BUDGET",INDEX($L:$L,MATCH(row_id,$X:$X,0)))) -> 6000 | AB24: 0 | AC24: 6000 | AD24: 0
C25: =C24+1 -> 28 | D25: 22 | E25: 0 | F25: 1 | G25: 0 | H25: 0 | I25: EXPENSES | J25: CLOTHING | K25: 150 | L25: 2400 | M25: 20 | N25: 28 | O25: =IF(is_cat,ADDRESS(sort_min_row,COLUMN(tracked))&":"&ADDRESS(sort_max_row,COLUMN(tracked)),"") -> $K$20:$K$28 | P25: =IF(is_cat,RANK(tracked,INDIRECT(tracked_range),0),"") -> 3 | Q25: =IF(is_cat,ADDRESS(sort_min_row,COLUMN(budget))&":"&ADDRESS(sort_max_row,COLUMN(budget)),"") -> $L$20:$L$28 | R25: =IF(is_cat,RANK(budget,INDIRECT(budget_range),0),"") -> 6 | S25: =IF(is_cat,_xlfn.NUMBERVALUE(tracked_rank & budget_rank),"") -> 36 | T25: =IF(is_cat,ADDRESS(sort_min_row,COLUMN(comb_rank)) & ":" & ADDRESS(sort_max_row,COLUMN(comb_rank)),"") -> $S$20:$S$28 | U25: =IF(is_cat,RANK(comb_rank,INDIRECT(comb_rank_range),1),"") -> 3 | V25: =IF(is_cat,ADDRESS(sort_min_row,COLUMN(comb_rank_norm))& ":" & ADDRESS(ROW(),COLUMN(comb_rank_norm)),"") -> $U$20:$U$25 | W25: =IF(is_cat,comb_rank_norm+COUNTIF(INDIRECT(comb_rank_norm_run_range),comb_rank_norm)-1,"") -> 3 | X25: =IF(is_cat,header_row_id+comb_rank_unique,row_id) -> 25 | Y25: =IF(is_empty,"",INDEX($J:$J,MATCH(row_id,$X:$X,0))) -> UTILITIES | Z25: 300 | AA25: =IF(is_empty,"",IF(is_header,"BUDGET",INDEX($L:$L,MATCH(row_id,$X:$X,0)))) -> 3600 | AB25: 0 | AC25: 3600 | AD25: 0
C26: =C25+1 -> 29 | D26: 22 | E26: 0 | F26: 1 | G26: 0 | H26: 0 | I26: EXPENSES | J26: BODY CARE & MEDICINE | K26: - | L26: 2400 | M26: 20 | N26: 28 | O26: =IF(is_cat,ADDRESS(sort_min_row,COLUMN(tracked))&":"&ADDRESS(sort_max_row,COLUMN(tracked)),"") -> $K$20:$K$28 | P26: 5 | Q26: =IF(is_cat,ADDRESS(sort_min_row,COLUMN(budget))&":"&ADDRESS(sort_max_row,COLUMN(budget)),"") -> $L$20:$L$28 | R26: =IF(is_cat,RANK(budget,INDIRECT(budget_range),0),"") -> 6 | S26: =IF(is_cat,_xlfn.NUMBERVALUE(tracked_rank & budget_rank),"") -> 56 | T26: =IF(is_cat,ADDRESS(sort_min_row,COLUMN(comb_rank)) & ":" & ADDRESS(sort_max_row,COLUMN(comb_rank)),"") -> $S$20:$S$28 | U26: =IF(is_cat,RANK(comb_rank,INDIRECT(comb_rank_range),1),"") -> 7 | V26: =IF(is_cat,ADDRESS(sort_min_row,COLUMN(comb_rank_norm))& ":" & ADDRESS(ROW(),COLUMN(comb_rank_norm)),"") -> $U$20:$U$26 | W26: =IF(is_cat,comb_rank_norm+COUNTIF(INDIRECT(comb_rank_norm_run_range),comb_rank_norm)-1,"") -> 7 | X26: =IF(is_cat,header_row_id+comb_rank_unique,row_id) -> 29 | Y26: =IF(is_empty,"",INDEX($J:$J,MATCH(row_id,$X:$X,0))) -> BODY CARE & MEDICINE | Z26: 270 | AA26: =IF(is_empty,"",IF(is_header,"BUDGET",INDEX($L:$L,MATCH(row_id,$X:$X,0)))) -> 2400 | AB26: 0 | AC26: 2400 | AD26: 0
C27: =C26+1 -> 30 | D27: 22 | E27: 0 | F27: 1 | G27: 0 | H27: 0 | I27: EXPENSES | J27: MEDIA | K27: - | L27: 600 | M27: 20 | N27: 28 | O27: =IF(is_cat,ADDRESS(sort_min_row,COLUMN(tracked))&":"&ADDRESS(sort_max_row,COLUMN(tracked)),"") -> $K$20:$K$28 | P27: 5 | Q27: =IF(is_cat,ADDRESS(sort_min_row,COLUMN(budget))&":"&ADDRESS(sort_max_row,COLUMN(budget)),"") -> $L$20:$L$28 | R27: =IF(is_cat,RANK(budget,INDIRECT(budget_range),0),"") -> 8 | S27: =IF(is_cat,_xlfn.NUMBERVALUE(tracked_rank & budget_rank),"") -> 58 | T27: =IF(is_cat,ADDRESS(sort_min_row,COLUMN(comb_rank)) & ":" & ADDRESS(sort_max_row,COLUMN(comb_rank)),"") -> $S$20:$S$28 | U27: =IF(is_cat,RANK(comb_rank,INDIRECT(comb_rank_range),1),"") -> 8 | V27: =IF(is_cat,ADDRESS(sort_min_row,COLUMN(comb_rank_norm))& ":" & ADDRESS(ROW(),COLUMN(comb_rank_norm)),"") -> $U$20:$U$27 | W27: =IF(is_cat,comb_rank_norm+COUNTIF(INDIRECT(comb_rank_norm_run_range),comb_rank_norm)-1,"") -> 9 | X27: =IF(is_cat,header_row_id+comb_rank_unique,row_id) -> 31 | Y27: =IF(is_empty,"",INDEX($J:$J,MATCH(row_id,$X:$X,0))) -> INSURANCES | AA27: =IF(is_empty,"",IF(is_header,"BUDGET",INDEX($L:$L,MATCH(row_id,$X:$X,0)))) -> 600 | AB27: 0 | AC27: 600 | AD27: 0
C28: 31 | D28: 22 | E28: 0 | F28: 1 | G28: 0 | H28: 0 | I28: EXPENSES | J28: FUN & VACATION | K28: - | L28: 6000 | M28: 20 | N28: 28 | O28: =IF(is_cat,ADDRESS(sort_min_row,COLUMN(tracked))&":"&ADDRESS(sort_max_row,COLUMN(tracked)),"") -> $K$20:$K$28 | P28: 5 | Q28: =IF(is_cat,ADDRESS(sort_min_row,COLUMN(budget))&":"&ADDRESS(sort_max_row,COLUMN(budget)),"") -> $L$20:$L$28 | R28: =IF(is_cat,RANK(budget,INDIRECT(budget_range),0),"") -> 2 | S28: =IF(is_cat,_xlfn.NUMBERVALUE(tracked_rank & budget_rank),"") -> 52 | T28: =IF(is_cat,ADDRESS(sort_min_row,COLUMN(comb_rank)) & ":" & ADDRESS(sort_max_row,COLUMN(comb_rank)),"") -> $S$20:$S$28 | U28: =IF(is_cat,RANK(comb_rank,INDIRECT(comb_rank_range),1),"") -> 5 | V28: =IF(is_cat,ADDRESS(sort_min_row,COLUMN(comb_rank_norm))& ":" & ADDRESS(ROW(),COLUMN(comb_rank_norm)),"") -> $U$20:$U$28 | W28: =IF(is_cat,comb_rank_norm+COUNTIF(INDIRECT(comb_rank_norm_run_range),comb_rank_norm)-1,"") -> 5 | X28: =IF(is_cat,header_row_id+comb_rank_unique,row_id) -> 27 | Y28: =IF(is_empty,"",INDEX($J:$J,MATCH(row_id,$X:$X,0))) -> MEDIA | Z28: 70 | AA28: =IF(is_empty,"",IF(is_header,"BUDGET",INDEX($L:$L,MATCH(row_id,$X:$X,0)))) -> 600 | AB28: 0 | AC28: 600 | AD28: 0
C29: 36 | D29: 22 | E29: 0 | F29: 0 | G29: 1 | H29: 0 | I29: EXPENSES | J29: TOTAL | K29: =SUM(K20:K25) -> 1650 | L29: =SUM(L20:L28) -> 37800 | M29: {=IF(is_cat,IF(header_row_id=INCOME_HEADER_ROW,MATCH(INCOME_MIN_ROW,$C:$C,0),""),"")} | O29: =IF(is_cat,ADDRESS(sort_min_row,COLUMN(tracked))&":"&ADDRESS(sort_max_row,COLUMN(tracked)),"") | P29: =IF(is_cat,RANK(tracked,INDIRECT(tracked_range),0),"") | Q29: =IF(is_cat,ADDRESS(sort_min_row,COLUMN(budget))&":"&ADDRESS(sort_max_row,COLUMN(budget)),"") | R29: =IF(is_cat,RANK(budget,INDIRECT(budget_range),0),"") | S29: =IF(is_cat,_xlfn.NUMBERVALUE(tracked_rank & budget_rank),"") | T29: =IF(is_cat,ADDRESS(sort_min_row,COLUMN(comb_rank)) & ":" & ADDRESS(sort_max_row,COLUMN(comb_rank)),"") | U29: =IF(is_cat,RANK(comb_rank,INDIRECT(comb_rank_range),1),"") | V29: =IF(is_cat,ADDRESS(sort_min_row,COLUMN(comb_rank_norm))& ":" & ADDRESS(ROW(),COLUMN(comb_rank_norm)),"") | W29: =IF(is_cat,comb_rank_norm+COUNTIF(INDIRECT(comb_rank_norm_run_range),comb_rank_norm)-1,"") | X29: =IF(is_cat,header_row_id+comb_rank_unique,row_id) -> 36 | Y29: =IF(is_empty,"",INDEX($J:$J,MATCH(row_id,$X:$X,0))) -> TOTAL | Z29: 3010 | AA29: =IF(is_empty,"",IF(is_header,"BUDGET",INDEX($L:$L,MATCH(row_id,$X:$X,0)))) -> 37800 | AB29: =IF(is_empty,"",IF(is_header,"%Compl.",IFERROR(out_tracked/out_budget,"-"))) -> 0.07962963 | AC29: =IF(is_empty,"",IF(is_header,"Remaining",IF(out_budget-out_tracked>0,out_budget-out_tracked,0))) -> 34790 | AD29: 0
D30: -1 | F30: 0 | H30: 1 | M30: {=IF(is_cat,IF(header_row_id=INCOME_HEADER_ROW,MATCH(INCOME_MIN_ROW,$C:$C,0),""),"")} | O30: =IF(is_cat,ADDRESS(sort_min_row,COLUMN(tracked))&":"&ADDRESS(sort_max_row,COLUMN(tracked)),"") | P30: =IF(is_cat,RANK(tracked,INDIRECT(tracked_range),0),"") | Q30: =IF(is_cat,ADDRESS(sort_min_row,COLUMN(budget))&":"&ADDRESS(sort_max_row,COLUMN(budget)),"") | R30: =IF(is_cat,RANK(budget,INDIRECT(budget_range),0),"") | S30: =IF(is_cat,_xlfn.NUMBERVALUE(tracked_rank & budget_rank),"") | T30: =IF(is_cat,ADDRESS(sort_min_row,COLUMN(comb_rank)) & ":" & ADDRESS(sort_max_row,COLUMN(comb_rank)),"") | U30: =IF(is_cat,RANK(comb_rank,INDIRECT(comb_rank_range),1),"") | V30: =IF(is_cat,ADDRESS(sort_min_row,COLUMN(comb_rank_norm))& ":" & ADDRESS(ROW(),COLUMN(comb_rank_norm)),"") | W30: =IF(is_cat,comb_rank_norm+COUNTIF(INDIRECT(comb_rank_norm_run_range),comb_rank_norm)-1,"") | X30: =IF(is_cat,header_row_id+comb_rank_unique,row_id) -> 0 | Y30: =IF(is_empty,"",INDEX($J:$J,MATCH(row_id,$X:$X,0))) | Z30: =IF(is_empty,"",IF(is_header,"TRACKED",INDEX($K:$K,MATCH(row_id,$X:$X,0)))) | AA30: =IF(is_empty,"",IF(is_header,"BUDGET",INDEX($L:$L,MATCH(row_id,$X:$X,0)))) | AB30: =IF(is_empty,"",IF(is_header,"%Compl.",IFERROR(out_tracked/out_budget,"-"))) | AC30: =IF(is_empty,"",IF(is_header,"Remaining",IF(out_budget-out_tracked>0,out_budget-out_tracked,0))) | AD30: 0 | AI30: Housing | AJ30: 1200 | AP30: Stock Portfolio | AQ30: 500
C31: 38 | D31: 38 | E31: 1 | F31: 0 | G31: 0 | H31: 0 | I31: SAVINGS | J31: SAVINGS | M31: {=IF(is_cat,IF(header_row_id=INCOME_HEADER_ROW,MATCH(INCOME_MIN_ROW,$C:$C,0),""),"")} | O31: =IF(is_cat,ADDRESS(sort_min_row,COLUMN(tracked))&":"&ADDRESS(sort_max_row,COLUMN(tracked)),"") | P31: =IF(is_cat,RANK(tracked,INDIRECT(tracked_range),0),"") | Q31: =IF(is_cat,ADDRESS(sort_min_row,COLUMN(budget))&":"&ADDRESS(sort_max_row,COLUMN(budget)),"") | R31: =IF(is_cat,RANK(budget,INDIRECT(budget_range),0),"") | S31: =IF(is_cat,_xlfn.NUMBERVALUE(tracked_rank & budget_rank),"") | T31: =IF(is_cat,ADDRESS(sort_min_row,COLUMN(comb_rank)) & ":" & ADDRESS(sort_max_row,COLUMN(comb_rank)),"") | U31: =IF(is_cat,RANK(comb_rank,INDIRECT(comb_rank_range),1),"") | V31: =IF(is_cat,ADDRESS(sort_min_row,COLUMN(comb_rank_norm))& ":" & ADDRESS(ROW(),COLUMN(comb_rank_norm)),"") | W31: =IF(is_cat,comb_rank_norm+COUNTIF(INDIRECT(comb_rank_norm_run_range),comb_rank_norm)-1,"") | X31: =IF(is_cat,header_row_id+comb_rank_unique,row_id) -> 38 | Y31: =IF(is_empty,"",INDEX($J:$J,MATCH(row_id,$X:$X,0))) -> SAVINGS | Z31: =IF(is_empty,"",IF(is_header,"TRACKED",INDEX($K:$K,MATCH(row_id,$X:$X,0)))) -> TRACKED | AA31: =IF(is_empty,"",IF(is_header,"BUDGET",INDEX($L:$L,MATCH(row_id,$X:$X,0)))) -> BUDGET | AB31: =IF(is_empty,"",IF(is_header,"%Compl.",IFERROR(out_tracked/out_budget,"-"))) -> %Compl. | AC31: =IF(is_empty,"",IF(is_header,"Remaining",IF(out_budget-out_tracked>0,out_budget-out_tracked,0))) -> Remaining | AD31: =IF(is_empty,"",IF(is_header,"Excess",IF(out_budget-out_tracked<0,out_tracked-out_budget,0))) -> Excess | AI31: Groceries | AJ31: 400 | AP31: Retirement Account | AQ31: 400
C32: =C31+1 -> 39 | D32: 38 | E32: 0 | F32: 1 | G32: 0 | H32: 0 | I32: SAVINGS | J32: EMERGENCY FUND | K32: 1000 | L32: 3000 | M32: 32 | N32: 36 | O32: =IF(is_cat,ADDRESS(sort_min_row,COLUMN(tracked))&":"&ADDRESS(sort_max_row,COLUMN(tracked)),"") -> $K$32:$K$36 | P32: =IF(is_cat,RANK(tracked,INDIRECT(tracked_range),0),"") -> 1 | Q32: =IF(is_cat,ADDRESS(sort_min_row,COLUMN(budget))&":"&ADDRESS(sort_max_row,COLUMN(budget)),"") -> $L$32:$L$36 | R32: =IF(is_cat,RANK(budget,INDIRECT(budget_range),0),"") -> 4 | S32: =IF(is_cat,_xlfn.NUMBERVALUE(tracked_rank & budget_rank),"") -> 14 | T32: =IF(is_cat,ADDRESS(sort_min_row,COLUMN(comb_rank)) & ":" & ADDRESS(sort_max_row,COLUMN(comb_rank)),"") -> $S$32:$S$36 | U32: =IF(is_cat,RANK(comb_rank,INDIRECT(comb_rank_range),1),"") -> 1 | V32: =IF(is_cat,ADDRESS(sort_min_row,COLUMN(comb_rank_norm))& ":" & ADDRESS(ROW(),COLUMN(comb_rank_norm)),"") -> $U$32:$U$32 | W32: =IF(is_cat,comb_rank_norm+COUNTIF(INDIRECT(comb_rank_norm_run_range),comb_rank_norm)-1,"") -> 1 | X32: =IF(is_cat,header_row_id+comb_rank_unique,row_id) -> 39 | Y32: =IF(is_empty,"",INDEX($J:$J,MATCH(row_id,$X:$X,0))) -> EMERGENCY FUND | Z32: 500 | AA32: =IF(is_empty,"",IF(is_header,"BUDGET",INDEX($L:$L,MATCH(row_id,$X:$X,0)))) -> 3000 | AB32: =IF(is_empty,"",IF(is_header,"%Compl.",IFERROR(out_tracked/out_budget,"-"))) -> 0.16666667 | AC32: =IF(is_empty,"",IF(is_header,"Remaining",IF(out_budget-out_tracked>0,out_budget-out_tracked,0))) -> 2500 | AD32: =IF(is_empty,"",IF(is_header,"Excess",IF(out_budget-out_tracked<0,out_tracked-out_budget,0))) -> 0 | AI32: Transportation | AJ32: 380 | AP32: Emergency Fund | AQ32: 140
C33: =C32+1 -> 40 | D33: 38 | E33: 0 | F33: 1 | G33: 0 | H33: 0 | I33: SAVINGS | J33: RETIREMENT ACCOUNT | K33: - | L33: 4800 | M33: 32 | N33: 36 | O33: =IF(is_cat,ADDRESS(sort_min_row,COLUMN(tracked))&":"&ADDRESS(sort_max_row,COLUMN(tracked)),"") -> $K$32:$K$36 | P33: 3 | Q33: =IF(is_cat,ADDRESS(sort_min_row,COLUMN(budget))&":"&ADDRESS(sort_max_row,COLUMN(budget)),"") -> $L$32:$L$36 | R33: =IF(is_cat,RANK(budget,INDIRECT(budget_range),0),"") -> 3 | S33: =IF(is_cat,_xlfn.NUMBERVALUE(tracked_rank & budget_rank),"") -> 33 | T33: =IF(is_cat,ADDRESS(sort_min_row,COLUMN(comb_rank)) & ":" & ADDRESS(sort_max_row,COLUMN(comb_rank)),"") -> $S$32:$S$36 | U33: =IF(is_cat,RANK(comb_rank,INDIRECT(comb_rank_range),1),"") -> 4 | V33: =IF(is_cat,ADDRESS(sort_min_row,COLUMN(comb_rank_norm))& ":" & ADDRESS(ROW(),COLUMN(comb_rank_norm)),"") -> $U$32:$U$33 | W33: =IF(is_cat,comb_rank_norm+COUNTIF(INDIRECT(comb_rank_norm_run_range),comb_rank_norm)-1,"") -> 4 | X33: =IF(is_cat,header_row_id+comb_rank_unique,row_id) -> 42 | Y33: =IF(is_empty,"",INDEX($J:$J,MATCH(row_id,$X:$X,0))) -> STOCK PORTFOLIO | Z33: 400 | AA33: =IF(is_empty,"",IF(is_header,"BUDGET",INDEX($L:$L,MATCH(row_id,$X:$X,0)))) -> 7200 | AB33: =IF(is_empty,"",IF(is_header,"%Compl.",IFERROR(out_tracked/out_budget,"-"))) -> 0.055555556 | AC33: =IF(is_empty,"",IF(is_header,"Remaining",IF(out_budget-out_tracked>0,out_budget-out_tracked,0))) -> 6800 | AD33: =IF(is_empty,"",IF(is_header,"Excess",IF(out_budget-out_tracked<0,out_tracked-out_budget,0))) -> 0 | AI33: Utilities | AJ33: 300 | AP33: Sinking Fund Rest | AQ33: 400
C34: =C33+1 -> 41 | D34: 38 | E34: 0 | F34: 1 | G34: 0 | H34: 0 | I34: SAVINGS | J34: STOCK PORTFOLIO | K34: 500 | L34: 7200 | M34: 32 | N34: 36 | O34: =IF(is_cat,ADDRESS(sort_min_row,COLUMN(tracked))&":"&ADDRESS(sort_max_row,COLUMN(tracked)),"") -> $K$32:$K$36 | P34: =IF(is_cat,RANK(tracked,INDIRECT(tracked_range),0),"") -> 2 | Q34: =IF(is_cat,ADDRESS(sort_min_row,COLUMN(budget))&":"&ADDRESS(sort_max_row,COLUMN(budget)),"") -> $L$32:$L$36 | R34: =IF(is_cat,RANK(budget,INDIRECT(budget_range),0),"") -> 2 | S34: =IF(is_cat,_xlfn.NUMBERVALUE(tracked_rank & budget_rank),"") -> 22 | T34: =IF(is_cat,ADDRESS(sort_min_row,COLUMN(comb_rank)) & ":" & ADDRESS(sort_max_row,COLUMN(comb_rank)),"") -> $S$32:$S$36 | U34: =IF(is_cat,RANK(comb_rank,INDIRECT(comb_rank_range),1),"") -> 2 | V34: =IF(is_cat,ADDRESS(sort_min_row,COLUMN(comb_rank_norm))& ":" & ADDRESS(ROW(),COLUMN(comb_rank_norm)),"") -> $U$32:$U$34 | W34: =IF(is_cat,comb_rank_norm+COUNTIF(INDIRECT(comb_rank_norm_run_range),comb_rank_norm)-1,"") -> 2 | X34: =IF(is_cat,header_row_id+comb_rank_unique,row_id) -> 40 | Y34: =IF(is_empty,"",INDEX($J:$J,MATCH(row_id,$X:$X,0))) -> SINKING FUND DOWN PAYMENT | Z34: 140 | AA34: =IF(is_empty,"",IF(is_header,"BUDGET",INDEX($L:$L,MATCH(row_id,$X:$X,0)))) -> 10200 | AB34: 0 | AC34: 10200 | AD34: 0 | AI34: Body Care & Medicine | AJ34: 270 | AP34: Sinking Fund Down Payment | AQ34: 140
C35: =C34+1 -> 42 | D35: 38 | E35: 0 | F35: 1 | G35: 0 | H35: 0 | I35: SAVINGS | J35: SINKING FUND DOWN PAYMENT | K35: - | L35: 10200 | M35: 32 | N35: 36 | O35: =IF(is_cat,ADDRESS(sort_min_row,COLUMN(tracked))&":"&ADDRESS(sort_max_row,COLUMN(tracked)),"") -> $K$32:$K$36 | P35: 3 | Q35: =IF(is_cat,ADDRESS(sort_min_row,COLUMN(budget))&":"&ADDRESS(sort_max_row,COLUMN(budget)),"") -> $L$32:$L$36 | R35: =IF(is_cat,RANK(budget,INDIRECT(budget_range),0),"") -> 1 | S35: =IF(is_cat,_xlfn.NUMBERVALUE(tracked_rank & budget_rank),"") -> 31 | T35: =IF(is_cat,ADDRESS(sort_min_row,COLUMN(comb_rank)) & ":" & ADDRESS(sort_max_row,COLUMN(comb_rank)),"") -> $S$32:$S$36 | U35: =IF(is_cat,RANK(comb_rank,INDIRECT(comb_rank_range),1),"") -> 3 | V35: =IF(is_cat,ADDRESS(sort_min_row,COLUMN(comb_rank_norm))& ":" & ADDRESS(ROW(),COLUMN(comb_rank_norm)),"") -> $U$32:$U$35 | W35: =IF(is_cat,comb_rank_norm+COUNTIF(INDIRECT(comb_rank_norm_run_range),comb_rank_norm)-1,"") -> 3 | X35: =IF(is_cat,header_row_id+comb_rank_unique,row_id) -> 41 | Y35: =IF(is_empty,"",INDEX($J:$J,MATCH(row_id,$X:$X,0))) -> RETIREMENT ACCOUNT | Z35: 800 | AA35: =IF(is_empty,"",IF(is_header,"BUDGET",INDEX($L:$L,MATCH(row_id,$X:$X,0)))) -> 4800 | AB35: 0 | AC35: 4800 | AD35: 0 | AI35: Other | AJ35: 460 | AP35: Other | AQ35: 850
C36: =C35+1 -> 43 | D36: 38 | E36: 0 | F36: 1 | G36: 0 | H36: 0 | I36: SAVINGS | J36: SINKING FUND REST | K36: - | L36: 1200 | M36: 32 | N36: 36 | O36: =IF(is_cat,ADDRESS(sort_min_row,COLUMN(tracked))&":"&ADDRESS(sort_max_row,COLUMN(tracked)),"") -> $K$32:$K$36 | P36: 3 | Q36: =IF(is_cat,ADDRESS(sort_min_row,COLUMN(budget))&":"&ADDRESS(sort_max_row,COLUMN(budget)),"") -> $L$32:$L$36 | R36: =IF(is_cat,RANK(budget,INDIRECT(budget_range),0),"") -> 5 | S36: =IF(is_cat,_xlfn.NUMBERVALUE(tracked_rank & budget_rank),"") -> 35 | T36: =IF(is_cat,ADDRESS(sort_min_row,COLUMN(comb_rank)) & ":" & ADDRESS(sort_max_row,COLUMN(comb_rank)),"") -> $S$32:$S$36 | U36: =IF(is_cat,RANK(comb_rank,INDIRECT(comb_rank_range),1),"") -> 5 | V36: =IF(is_cat,ADDRESS(sort_min_row,COLUMN(comb_rank_norm))& ":" & ADDRESS(ROW(),COLUMN(comb_rank_norm)),"") -> $U$32:$U$36 | W36: =IF(is_cat,comb_rank_norm+COUNTIF(INDIRECT(comb_rank_norm_run_range),comb_rank_norm)-1,"") -> 5 | X36: =IF(is_cat,header_row_id+comb_rank_unique,row_id) -> 43 | Y36: =IF(is_empty,"",INDEX($J:$J,MATCH(row_id,$X:$X,0))) -> SINKING FUND REST | Z36: 400 | AA36: =IF(is_empty,"",IF(is_header,"BUDGET",INDEX($L:$L,MATCH(row_id,$X:$X,0)))) -> 1200 | AB36: 0 | AC36: 1200 | AD36: 0 | AI36: TOTAL | AJ36: =SUM(AJ30:AK35) -> 3010 | AP36: TOTAL | AQ36: =SUM(AQ30:AR35) -> 2430
C37: =49 -> 49 | D37: 38 | E37: 0 | F37: 0 | G37: 1 | H37: 0 | I37: SAVINGS | J37: TOTAL | K37: =SUM(K32:K34) -> 1500 | L37: =SUM(L32:L36) -> 26400 | M37: {=IF(is_cat,IF(header_row_id=INCOME_HEADER_ROW,MATCH(INCOME_MIN_ROW,$C:$C,0),""),"")} | O37: =IF(is_cat,ADDRESS(sort_min_row,COLUMN(tracked))&":"&ADDRESS(sort_max_row,COLUMN(tracked)),"") | P37: =IF(is_cat,RANK(tracked,INDIRECT(tracked_range),0),"") | Q37: =IF(is_cat,ADDRESS(sort_min_row,COLUMN(budget))&":"&ADDRESS(sort_max_row,COLUMN(budget)),"") | R37: =IF(is_cat,RANK(budget,INDIRECT(budget_range),0),"") | S37: =IF(is_cat,_xlfn.NUMBERVALUE(tracked_rank & budget_rank),"") | T37: =IF(is_cat,ADDRESS(sort_min_row,COLUMN(comb_rank)) & ":" & ADDRESS(sort_max_row,COLUMN(comb_rank)),"") | U37: =IF(is_cat,RANK(comb_rank,INDIRECT(comb_rank_range),1),"") | V37: =IF(is_cat,ADDRESS(sort_min_row,COLUMN(comb_rank_norm))& ":" & ADDRESS(ROW(),COLUMN(comb_rank_norm)),"") | W37: =IF(is_cat,comb_rank_norm+COUNTIF(INDIRECT(comb_rank_norm_run_range),comb_rank_norm)-1,"") | X37: =IF(is_cat,header_row_id+comb_rank_unique,row_id) -> 49 | Y37: =IF(is_empty,"",INDEX($J:$J,MATCH(row_id,$X:$X,0))) -> TOTAL | Z37: 1040 | AA37: =IF(is_empty,"",IF(is_header,"BUDGET",INDEX($L:$L,MATCH(row_id,$X:$X,0)))) -> 26400 | AB37: =IF(is_empty,"",IF(is_header,"%Compl.",IFERROR(out_tracked/out_budget,"-"))) -> 0.039393939 | AC37: =IF(is_empty,"",IF(is_header,"Remaining",IF(out_budget-out_tracked>0,out_budget-out_tracked,0))) -> 25360 | AD37: =IF(is_empty,"",IF(is_header,"Excess",IF(out_budget-out_tracked<0,out_tracked-out_budget,0))) -> 0
C38: -1 | D38: -1 | E38: 0 | F38: 0 | G38: 0 | H38: 1 | M38: {=IF(is_cat,IF(header_row_id=INCOME_HEADER_ROW,MATCH(INCOME_MIN_ROW,$C:$C,0),""),"")} | O38: =IF(is_cat,ADDRESS(sort_min_row,COLUMN(tracked))&":"&ADDRESS(sort_max_row,COLUMN(tracked)),"") | P38: =IF(is_cat,RANK(tracked,INDIRECT(tracked_range),0),"") | Q38: =IF(is_cat,ADDRESS(sort_min_row,COLUMN(budget))&":"&ADDRESS(sort_max_row,COLUMN(budget)),"") | R38: =IF(is_cat,RANK(budget,INDIRECT(budget_range),0),"") | S38: =IF(is_cat,_xlfn.NUMBERVALUE(tracked_rank & budget_rank),"") | T38: =IF(is_cat,ADDRESS(sort_min_row,COLUMN(comb_rank)) & ":" & ADDRESS(sort_max_row,COLUMN(comb_rank)),"") | U38: =IF(is_cat,RANK(comb_rank,INDIRECT(comb_rank_range),1),"") | V38: =IF(is_cat,ADDRESS(sort_min_row,COLUMN(comb_rank_norm))& ":" & ADDRESS(ROW(),COLUMN(comb_rank_norm)),"") | W38: =IF(is_cat,comb_rank_norm+COUNTIF(INDIRECT(comb_rank_norm_run_range),comb_rank_norm)-1,"") | X38: =IF(is_cat,header_row_id+comb_rank_unique,row_id) -> -1
C39: -1 | D39: -1 | E39: 0 | F39: 0 | G39: 0 | H39: 1 | M39: {=IF(is_cat,IF(header_row_id=INCOME_HEADER_ROW,MATCH(INCOME_MIN_ROW,$C:$C,0),""),"")} | O39: =IF(is_cat,ADDRESS(sort_min_row,COLUMN(tracked))&":"&ADDRESS(sort_max_row,COLUMN(tracked)),"") | P39: =IF(is_cat,RANK(tracked,INDIRECT(tracked_range),0),"") | Q39: =IF(is_cat,ADDRESS(sort_min_row,COLUMN(budget))&":"&ADDRESS(sort_max_row,COLUMN(budget)),"") | R39: =IF(is_cat,RANK(budget,INDIRECT(budget_range),0),"") | S39: =IF(is_cat,_xlfn.NUMBERVALUE(tracked_rank & budget_rank),"") | T39: =IF(is_cat,ADDRESS(sort_min_row,COLUMN(comb_rank)) & ":" & ADDRESS(sort_max_row,COLUMN(comb_rank)),"") | U39: =IF(is_cat,RANK(comb_rank,INDIRECT(comb_rank_range),1),"") | V39: =IF(is_cat,ADDRESS(sort_min_row,COLUMN(comb_rank_norm))& ":" & ADDRESS(ROW(),COLUMN(comb_rank_norm)),"") | W39: =IF(is_cat,comb_rank_norm+COUNTIF(INDIRECT(comb_rank_norm_run_range),comb_rank_norm)-1,"") | X39: =IF(is_cat,header_row_id+comb_rank_unique,row_id) -> -1
C40: -1 | D40: -1 | E40: 0 | F40: 0 | G40: 0 | H40: 1 | M40: {=IF(is_cat,IF(header_row_id=INCOME_HEADER_ROW,MATCH(INCOME_MIN_ROW,$C:$C,0),""),"")} | O40: =IF(is_cat,ADDRESS(sort_min_row,COLUMN(tracked))&":"&ADDRESS(sort_max_row,COLUMN(tracked)),"") | P40: =IF(is_cat,RANK(tracked,INDIRECT(tracked_range),0),"") | Q40: =IF(is_cat,ADDRESS(sort_min_row,COLUMN(budget))&":"&ADDRESS(sort_max_row,COLUMN(budget)),"") | R40: =IF(is_cat,RANK(budget,INDIRECT(budget_range),0),"") | S40: =IF(is_cat,_xlfn.NUMBERVALUE(tracked_rank & budget_rank),"") | T40: =IF(is_cat,ADDRESS(sort_min_row,COLUMN(comb_rank)) & ":" & ADDRESS(sort_max_row,COLUMN(comb_rank)),"") | U40: =IF(is_cat,RANK(comb_rank,INDIRECT(comb_rank_range),1),"") | V40: =IF(is_cat,ADDRESS(sort_min_row,COLUMN(comb_rank_norm))& ":" & ADDRESS(ROW(),COLUMN(comb_rank_norm)),"") | W40: =IF(is_cat,comb_rank_norm+COUNTIF(INDIRECT(comb_rank_norm_run_range),comb_rank_norm)-1,"") | X40: =IF(is_cat,header_row_id+comb_rank_unique,row_id) -> -1
C41: -1 | D41: -1 | E41: 0 | F41: 0 | G41: 0 | H41: 1 | M41: {=IF(is_cat,IF(header_row_id=INCOME_HEADER_ROW,MATCH(INCOME_MIN_ROW,$C:$C,0),""),"")} | O41: =IF(is_cat,ADDRESS(sort_min_row,COLUMN(tracked))&":"&ADDRESS(sort_max_row,COLUMN(tracked)),"") | P41: =IF(is_cat,RANK(tracked,INDIRECT(tracked_range),0),"") | Q41: =IF(is_cat,ADDRESS(sort_min_row,COLUMN(budget))&":"&ADDRESS(sort_max_row,COLUMN(budget)),"") | R41: =IF(is_cat,RANK(budget,INDIRECT(budget_range),0),"") | S41: =IF(is_cat,_xlfn.NUMBERVALUE(tracked_rank & budget_rank),"") | T41: =IF(is_cat,ADDRESS(sort_min_row,COLUMN(comb_rank)) & ":" & ADDRESS(sort_max_row,COLUMN(comb_rank)),"") | U41: =IF(is_cat,RANK(comb_rank,INDIRECT(comb_rank_range),1),"") | V41: =IF(is_cat,ADDRESS(sort_min_row,COLUMN(comb_rank_norm))& ":" & ADDRESS(ROW(),COLUMN(comb_rank_norm)),"") | W41: =IF(is_cat,comb_rank_norm+COUNTIF(INDIRECT(comb_rank_norm_run_range),comb_rank_norm)-1,"") | X41: =IF(is_cat,header_row_id+comb_rank_unique,row_id) -> -1
C42: -1 | D42: -1 | E42: 0 | F42: 0 | G42: 0 | H42: 1 | M42: {=IF(is_cat,IF(header_row_id=INCOME_HEADER_ROW,MATCH(INCOME_MIN_ROW,$C:$C,0),""),"")} | O42: =IF(is_cat,ADDRESS(sort_min_row,COLUMN(tracked))&":"&ADDRESS(sort_max_row,COLUMN(tracked)),"") | P42: =IF(is_cat,RANK(tracked,INDIRECT(tracked_range),0),"") | Q42: =IF(is_cat,ADDRESS(sort_min_row,COLUMN(budget))&":"&ADDRESS(sort_max_row,COLUMN(budget)),"") | R42: =IF(is_cat,RANK(budget,INDIRECT(budget_range),0),"") | S42: =IF(is_cat,_xlfn.NUMBERVALUE(tracked_rank & budget_rank),"") | T42: =IF(is_cat,ADDRESS(sort_min_row,COLUMN(comb_rank)) & ":" & ADDRESS(sort_max_row,COLUMN(comb_rank)),"") | U42: =IF(is_cat,RANK(comb_rank,INDIRECT(comb_rank_range),1),"") | V42: =IF(is_cat,ADDRESS(sort_min_row,COLUMN(comb_rank_norm))& ":" & ADDRESS(ROW(),COLUMN(comb_rank_norm)),"") | W42: =IF(is_cat,comb_rank_norm+COUNTIF(INDIRECT(comb_rank_norm_run_range),comb_rank_norm)-1,"") | X42: =IF(is_cat,header_row_id+comb_rank_unique,row_id) -> -1
C43: -1 | D43: -1 | E43: 0 | F43: 0 | G43: 0 | H43: 1 | M43: {=IF(is_cat,IF(header_row_id=INCOME_HEADER_ROW,MATCH(INCOME_MIN_ROW,$C:$C,0),""),"")} | O43: =IF(is_cat,ADDRESS(sort_min_row,COLUMN(tracked))&":"&ADDRESS(sort_max_row,COLUMN(tracked)),"") | P43: =IF(is_cat,RANK(tracked,INDIRECT(tracked_range),0),"") | Q43: =IF(is_cat,ADDRESS(sort_min_row,COLUMN(budget))&":"&ADDRESS(sort_max_row,COLUMN(budget)),"") | R43: =IF(is_cat,RANK(budget,INDIRECT(budget_range),0),"") | S43: =IF(is_cat,_xlfn.NUMBERVALUE(tracked_rank & budget_rank),"") | T43: =IF(is_cat,ADDRESS(sort_min_row,COLUMN(comb_rank)) & ":" & ADDRESS(sort_max_row,COLUMN(comb_rank)),"") | U43: =IF(is_cat,RANK(comb_rank,INDIRECT(comb_rank_range),1),"") | V43: =IF(is_cat,ADDRESS(sort_min_row,COLUMN(comb_rank_norm))& ":" & ADDRESS(ROW(),COLUMN(comb_rank_norm)),"") | W43: =IF(is_cat,comb_rank_norm+COUNTIF(INDIRECT(comb_rank_norm_run_range),comb_rank_norm)-1,"") | X43: =IF(is_cat,header_row_id+comb_rank_unique,row_id) -> -1
C44: -1 | D44: -1 | E44: 0 | F44: 0 | G44: 0 | H44: 1 | M44: {=IF(is_cat,IF(header_row_id=INCOME_HEADER_ROW,MATCH(INCOME_MIN_ROW,$C:$C,0),""),"")} | O44: =IF(is_cat,ADDRESS(sort_min_row,COLUMN(tracked))&":"&ADDRESS(sort_max_row,COLUMN(tracked)),"") | P44: =IF(is_cat,RANK(tracked,INDIRECT(tracked_range),0),"") | Q44: =IF(is_cat,ADDRESS(sort_min_row,COLUMN(budget))&":"&ADDRESS(sort_max_row,COLUMN(budget)),"") | R44: =IF(is_cat,RANK(budget,INDIRECT(budget_range),0),"") | S44: =IF(is_cat,_xlfn.NUMBERVALUE(tracked_rank & budget_rank),"") | T44: =IF(is_cat,ADDRESS(sort_min_row,COLUMN(comb_rank)) & ":" & ADDRESS(sort_max_row,COLUMN(comb_rank)),"") | U44: =IF(is_cat,RANK(comb_rank,INDIRECT(comb_rank_range),1),"") | V44: =IF(is_cat,ADDRESS(sort_min_row,COLUMN(comb_rank_norm))& ":" & ADDRESS(ROW(),COLUMN(comb_rank_norm)),"") | W44: =IF(is_cat,comb_rank_norm+COUNTIF(INDIRECT(comb_rank_norm_run_range),comb_rank_norm)-1,"") | X44: =IF(is_cat,header_row_id+comb_rank_unique,row_id) -> -1
C45: -1 | D45: -1 | E45: 0 | F45: 0 | G45: 0 | H45: 1 | M45: {=IF(is_cat,IF(header_row_id=INCOME_HEADER_ROW,MATCH(INCOME_MIN_ROW,$C:$C,0),""),"")} | O45: =IF(is_cat,ADDRESS(sort_min_row,COLUMN(tracked))&":"&ADDRESS(sort_max_row,COLUMN(tracked)),"") | P45: =IF(is_cat,RANK(tracked,INDIRECT(tracked_range),0),"") | Q45: =IF(is_cat,ADDRESS(sort_min_row,COLUMN(budget))&":"&ADDRESS(sort_max_row,COLUMN(budget)),"") | R45: =IF(is_cat,RANK(budget,INDIRECT(budget_range),0),"") | S45: =IF(is_cat,_xlfn.NUMBERVALUE(tracked_rank & budget_rank),"") | T45: =IF(is_cat,ADDRESS(sort_min_row,COLUMN(comb_rank)) & ":" & ADDRESS(sort_max_row,COLUMN(comb_rank)),"") | U45: =IF(is_cat,RANK(comb_rank,INDIRECT(comb_rank_range),1),"") | V45: =IF(is_cat,ADDRESS(sort_min_row,COLUMN(comb_rank_norm))& ":" & ADDRESS(ROW(),COLUMN(comb_rank_norm)),"") | W45: =IF(is_cat,comb_rank_norm+COUNTIF(INDIRECT(comb_rank_norm_run_range),comb_rank_norm)-1,"") | X45: =IF(is_cat,header_row_id+comb_rank_unique,row_id) -> -1
C46: -1 | D46: -1 | E46: 0 | F46: 0 | G46: 0 | H46: 1 | M46: {=IF(is_cat,IF(header_row_id=INCOME_HEADER_ROW,MATCH(INCOME_MIN_ROW,$C:$C,0),""),"")} | O46: =IF(is_cat,ADDRESS(sort_min_row,COLUMN(tracked))&":"&ADDRESS(sort_max_row,COLUMN(tracked)),"") | P46: =IF(is_cat,RANK(tracked,INDIRECT(tracked_range),0),"") | Q46: =IF(is_cat,ADDRESS(sort_min_row,COLUMN(budget))&":"&ADDRESS(sort_max_row,COLUMN(budget)),"") | R46: =IF(is_cat,RANK(budget,INDIRECT(budget_range),0),"") | S46: =IF(is_cat,_xlfn.NUMBERVALUE(tracked_rank & budget_rank),"") | T46: =IF(is_cat,ADDRESS(sort_min_row,COLUMN(comb_rank)) & ":" & ADDRESS(sort_max_row,COLUMN(comb_rank)),"") | U46: =IF(is_cat,RANK(comb_rank,INDIRECT(comb_rank_range),1),"") | V46: =IF(is_cat,ADDRESS(sort_min_row,COLUMN(comb_rank_norm))& ":" & ADDRESS(ROW(),COLUMN(comb_rank_norm)),"") | W46: =IF(is_cat,comb_rank_norm+COUNTIF(INDIRECT(comb_rank_norm_run_range),comb_rank_norm)-1,"") | X46: =IF(is_cat,header_row_id+comb_rank_unique,row_id) -> -1
C47: -1 | D47: -1 | E47: 0 | F47: 0 | G47: 0 | H47: 1 | M47: {=IF(is_cat,IF(header_row_id=INCOME_HEADER_ROW,MATCH(INCOME_MIN_ROW,$C:$C,0),""),"")} | O47: =IF(is_cat,ADDRESS(sort_min_row,COLUMN(tracked))&":"&ADDRESS(sort_max_row,COLUMN(tracked)),"") | P47: =IF(is_cat,RANK(tracked,INDIRECT(tracked_range),0),"") | Q47: =IF(is_cat,ADDRESS(sort_min_row,COLUMN(budget))&":"&ADDRESS(sort_max_row,COLUMN(budget)),"") | R47: =IF(is_cat,RANK(budget,INDIRECT(budget_range),0),"") | S47: =IF(is_cat,_xlfn.NUMBERVALUE(tracked_rank & budget_rank),"") | T47: =IF(is_cat,ADDRESS(sort_min_row,COLUMN(comb_rank)) & ":" & ADDRESS(sort_max_row,COLUMN(comb_rank)),"") | U47: =IF(is_cat,RANK(comb_rank,INDIRECT(comb_rank_range),1),"") | V47: =IF(is_cat,ADDRESS(sort_min_row,COLUMN(comb_rank_norm))& ":" & ADDRESS(ROW(),COLUMN(comb_rank_norm)),"") | W47: =IF(is_cat,comb_rank_norm+COUNTIF(INDIRECT(comb_rank_norm_run_range),comb_rank_norm)-1,"") | X47: =IF(is_cat,header_row_id+comb_rank_unique,row_id) -> -1
C48: -1 | D48: -1 | E48: 0 | F48: 0 | G48: 0 | H48: 1 | M48: {=IF(is_cat,IF(header_row_id=INCOME_HEADER_ROW,MATCH(INCOME_MIN_ROW,$C:$C,0),""),"")} | O48: =IF(is_cat,ADDRESS(sort_min_row,COLUMN(tracked))&":"&ADDRESS(sort_max_row,COLUMN(tracked)),"") | P48: =IF(is_cat,RANK(tracked,INDIRECT(tracked_range),0),"") | Q48: =IF(is_cat,ADDRESS(sort_min_row,COLUMN(budget))&":"&ADDRESS(sort_max_row,COLUMN(budget)),"") | R48: =IF(is_cat,RANK(budget,INDIRECT(budget_range),0),"") | S48: =IF(is_cat,_xlfn.NUMBERVALUE(tracked_rank & budget_rank),"") | T48: =IF(is_cat,ADDRESS(sort_min_row,COLUMN(comb_rank)) & ":" & ADDRESS(sort_max_row,COLUMN(comb_rank)),"") | U48: =IF(is_cat,RANK(comb_rank,INDIRECT(comb_rank_range),1),"") | V48: =IF(is_cat,ADDRESS(sort_min_row,COLUMN(comb_rank_norm))& ":" & ADDRESS(ROW(),COLUMN(comb_rank_norm)),"") | W48: =IF(is_cat,comb_rank_norm+COUNTIF(INDIRECT(comb_rank_norm_run_range),comb_rank_norm)-1,"") | X48: =IF(is_cat,header_row_id+comb_rank_unique,row_id) -> -1
C49: -1 | D49: -1 | E49: TRUE | F49: 0 | G49: 0 | H49: 1 | M49: {=IF(is_cat,IF(header_row_id=INCOME_HEADER_ROW,MATCH(INCOME_MIN_ROW,$C:$C,0),""),"")} | O49: =IF(is_cat,ADDRESS(sort_min_row,COLUMN(tracked))&":"&ADDRESS(sort_max_row,COLUMN(tracked)),"") | P49: =IF(is_cat,RANK(tracked,INDIRECT(tracked_range),0),"") | Q49: =IF(is_cat,ADDRESS(sort_min_row,COLUMN(budget))&":"&ADDRESS(sort_max_row,COLUMN(budget)),"") | R49: =IF(is_cat,RANK(budget,INDIRECT(budget_range),0),"") | S49: =IF(is_cat,_xlfn.NUMBERVALUE(tracked_rank & budget_rank),"") | T49: =IF(is_cat,ADDRESS(sort_min_row,COLUMN(comb_rank)) & ":" & ADDRESS(sort_max_row,COLUMN(comb_rank)),"") | U49: =IF(is_cat,RANK(comb_rank,INDIRECT(comb_rank_range),1),"") | V49: =IF(is_cat,ADDRESS(sort_min_row,COLUMN(comb_rank_norm))& ":" & ADDRESS(ROW(),COLUMN(comb_rank_norm)),"") | W49: =IF(is_cat,comb_rank_norm+COUNTIF(INDIRECT(comb_rank_norm_run_range),comb_rank_norm)-1,"") | X49: =IF(is_cat,header_row_id+comb_rank_unique,row_id) -> -1
C50: -1 | D50: -1 | E50: TRUE | F50: 0 | G50: 0 | H50: 1 | M50: {=IF(is_cat,IF(header_row_id=INCOME_HEADER_ROW,MATCH(INCOME_MIN_ROW,$C:$C,0),""),"")} | O50: =IF(is_cat,ADDRESS(sort_min_row,COLUMN(tracked))&":"&ADDRESS(sort_max_row,COLUMN(tracked)),"") | P50: =IF(is_cat,RANK(tracked,INDIRECT(tracked_range),0),"") | Q50: =IF(is_cat,ADDRESS(sort_min_row,COLUMN(budget))&":"&ADDRESS(sort_max_row,COLUMN(budget)),"") | R50: =IF(is_cat,RANK(budget,INDIRECT(budget_range),0),"") | S50: =IF(is_cat,_xlfn.NUMBERVALUE(tracked_rank & budget_rank),"") | T50: =IF(is_cat,ADDRESS(sort_min_row,COLUMN(comb_rank)) & ":" & ADDRESS(sort_max_row,COLUMN(comb_rank)),"") | U50: =IF(is_cat,RANK(comb_rank,INDIRECT(comb_rank_range),1),"") | V50: =IF(is_cat,ADDRESS(sort_min_row,COLUMN(comb_rank_norm))& ":" & ADDRESS(ROW(),COLUMN(comb_rank_norm)),"") | W50: =IF(is_cat,comb_rank_norm+COUNTIF(INDIRECT(comb_rank_norm_run_range),comb_rank_norm)-1,"") | X50: =IF(is_cat,header_row_id+comb_rank_unique,row_id) -> -1
E51: TRUE | W51: =IF(is_cat,comb_rank_norm+COUNTIF(INDIRECT(comb_rank_norm_run_range),comb_rank_norm)-1,"")
E52: FALSE

Sheet CALCULATIONS
A1: CALCUALTIONS
C6: Worksheet: Budget Tracking
D8: Today:- | E8: {=current_date} -> 44635
D9: Last Record:- | E9: =MAX(TRACKING[Date]) -> 44635
D10: Delta Last Record:- | E10: =IF(E9=0,"","("&_xlfn.DAYS(E8,E9)&"days ago)") -> (0days ago)
D11: #Records:- | E11: =COUNT(TRACKING[Date]) -> 58
D12: #Records this year:- | E12: {="("& SUMPRODUCT(--(YEAR(TRACKING[Date])=YEAR(current_date))) & "this year)"} -> (56this year)
D13: TRACKING BALANCE:- | E13: =_xlfn.IFNA(INDEX(TRACKING[BALANCE],MATCH(CALCULATIONS!E9,TRACKING[Date],0)),"-") -> 24280
D14: BALANCE ANALYSIS TEXT:- | E14: =IF(E13>=0,"of tracked income left to be allocated","allocated not covered by income") -> of tracked income left to be allocated
C17: Worksheet: Budget Dashboard
D19: Selected Year:- | E19: {=IF('BUDGET DASHBOARD'!$AQ$6="Current Year",YEAR(current_date),'BUDGET DASHBOARD'!$AQ$6)} -> 0
D20: Selected Period:- | E20: {=IF('BUDGET DASHBOARD'!$AQ$9="Total Year","Total Year",IF('BUDGET DASHBOARD'!$AQ$9="Current Month",MONTH(current_date),MONTH('BUDGET DASHBOARD'!$AQ$9)))} -> 1
D21: Selected Period (Display):- | E21: March
D22: Days in period:- | E22: 365
D23: Days passed in period:- | E23: 74
D24: Days passed in period %:- | E24: =E23/E22 -> 0.20273973
D25: Period Tracking Balance:- | E25: 2620
D32: Chart Calculations: Category Distribution Charts
D34: INCOME | E34: CATEGORY | F34: AMOUNT | H34: EXPENSES | I34: CATEGORY | J34: AMOUNT | L34: SAVINGS | M34: CATEGORY | N34: AMOUNT
D35: 1 | E35: Employment(Net) | F35: 3500 | H35: 1 | I35: Housing | J35: 1200 | L35: 1 | M35: Stock Portfolio | N35: 400
D36: 2 | E36: Side Hustle(Net) | F36: 500 | H36: 2 | I36: Groceries | J36: 400 | L36: 2 | M36: Retirement Account | N36: 800
D37: 3 | E37: Dividends | F37: 50 | H37: 3 | I37: Transportation | J37: 380 | L37: 3 | M37: Emergency Fund | N37: 500
D38: 4 | H38: 4 | I38: Utilities | J38: 300 | L38: 4 | M38: Sinking Fund Rest | N38: 400
D39: 5 | H39: 5 | I39: Body Care & Medicine | J39: 270 | L39: 5 | M39: Sinking Fund Down Payment | N39: 140
D40: 6 | H40: 6 | I40: Other | J40: 460 | L40: 6 | M40: Other | N40: 850
E41: TOTAL | F41: =SUM(F35:F40) -> 4050 | I41: TOTAL | J41: =SUM(J35:J40) -> 3010 | M41: TOTAL | N41: =SUM(N35:N40) -> 3090
D47: Chart Calculations: Tracked (Vs.Budget)
D49: SHOW INCOME: | E49: FALSE
D50: SHOW EXPENSES: | E50: FALSE
D51: SHOW SAVINGS: | E51: TRUE
D52: SHOW REM.BUDGET: | E52: FALSE
M53: PERIOD IN FOCUS | P53: PERIOD NOT IN FOCUS
D54: MONTH | E54: TYPE | F54: MONTH NUM | G54: IN FOCUS | H54: SHOW TYPE | I54: SHOW REM.BUDGET | J54: TRACKED | K54: BUDGET | L54: DELTA | M54: IN BUDGET | N54: REMAINING | O54: EXCESS | P54: IN BUDGET | Q54: REMAINING | R54: EXCESS
D55: =DATE(STARTING_YEAR,1,1) -> 44562 | E55: Income | F55: =MONTH(D55) -> 1 | G55: =IF(selected_period="TOTAL YEAR",1,IF(selected_period=cc_month,1,0)) -> 1 | H55: =1*$E$49 -> 0 | I55: =1*$E$52 -> 0 | J55: 4850 | K55: 4650 | L55: -200 | M55: - | N55: =IF(cc_delta>0,cc_delta,0) -> 0 | O55: =IF(cc_delta<0,ABS(cc_delta),0) -> 200 | P55: 4650 | Q55: - | R55: 200
E56: Expenses | F56: 1 | G56: =IF(selected_period="TOTAL YEAR",1,IF(selected_period=cc_month,1,0)) -> 1 | H56: =1*$E$50 -> 0 | I56: =1*$E$52 -> 0 | J56: 2800 | K56: 2900 | L56: 100 | M56: - | N56: =IF(cc_delta>0,cc_delta,0) -> 100 | O56: =IF(cc_delta<0,ABS(cc_delta),0) -> 0 | P56: 2800 | Q56: 100 | R56: -
E57: Savings | F57: 1 | G57: =IF(selected_period="TOTAL YEAR",1,IF(selected_period=cc_month,1,0)) -> 1 | H57: =1*$E$51 -> 1 | I57: =1*$E$52 -> 0 | J57: 2050 | K57: 1750 | L57: -300 | M57: - | N57: =IF(cc_delta>0,cc_delta,0) -> 0 | O57: =IF(cc_delta<0,ABS(cc_delta),0) -> 300 | P57: 1750 | Q57: - | R57: 300
D59: =DATE(STARTING_YEAR,2,1) -> 44593 | E59: Income | F59: 2 | H59: =1*$E$49 -> 0 | I59: =1*$E$52 -> 0 | J59: 4050 | K59: 4550 | L59: 500 | M59: =MIN(cc_tracked,cc_budget) -> 4050 | N59: =IF(cc_delta>0,cc_delta,0) -> 500 | O59: =IF(cc_delta<0,ABS(cc_delta),0) -> 0 | P59: - | Q59: - | R59: 201
E60: Expenses | F60: 2 | H60: =1*$E$50 -> 0 | I60: =1*$E$52 -> 0 | J60: 3010 | K60: 2900 | L60: -110 | M60: =MIN(cc_tracked,cc_budget) -> 2900 | N60: =IF(cc_delta>0,cc_delta,0) -> 0 | O60: =IF(cc_delta<0,ABS(cc_delta),0) -> 110 | P60: - | Q60: 100 | R60: -
E61: Savings | F61: 2 | H61: =1*$E$51 -> 1 | I61: =1*$E$52 -> 0 | J61: 1040 | K61: 1650 | L61: 610 | M61: =MIN(cc_tracked,cc_budget) -> 1040 | N61: =IF(cc_delta>0,cc_delta,0) -> 610 | O61: =IF(cc_delta<0,ABS(cc_delta),0) -> 0 | P61: - | Q61: - | R61: 301
D63: =DATE(STARTING_YEAR,3,1) -> 44621 | E63: Income | F63: 3 | H63: =1*$E$49 -> 0 | I63: =1*$E$52 -> 0 | J63: 4700 | K63: 4600 | L63: -100 | M63: =MIN(cc_tracked,cc_budget) -> 4600 | N63: =IF(cc_delta>0,cc_delta,0) -> 0 | O63: =IF(cc_delta<0,ABS(cc_delta),0) -> 100 | P63: - | Q63: - | R63: 202
E64: Expenses | F64: 3 | H64: =1*$E$50 -> 0 | I64: =1*$E$52 -> 0 | J64: 2080 | K64: 3050 | L64: 970 | M64: =MIN(cc_tracked,cc_budget) -> 2080 | N64: =IF(cc_delta>0,cc_delta,0) -> 970 | O64: =IF(cc_delta<0,ABS(cc_delta),0) -> 0 | P64: - | Q64: 100 | R64: -
E65: Savings | F65: 3 | H65: =1*$E$51 -> 1 | I65: =1*$E$52 -> 0 | J65: - | K65: 1550 | L65: 1550 | M65: =MIN(cc_tracked,cc_budget) -> 1550 | N65: =IF(cc_delta>0,cc_delta,0) -> 1550 | O65: =IF(cc_delta<0,ABS(cc_delta),0) -> 0 | P65: - | Q65: - | R65: 302
J66: -
D67: =DATE(STARTING_YEAR,4,1) -> 44652 | E67: Income | F67: 4 | H67: =1*$E$49 -> 0 | I67: =1*$E$52 -> 0 | J67: - | K67: 5650 | L67: 5650 | M67: - | N67: =IF(cc_delta>0,cc_delta,0) -> 5650 | O67: =IF(cc_delta<0,ABS(cc_delta),0) -> 0 | P67: - | Q67: - | R67: 203
E68: Expenses | F68: 4 | H68: =1*$E$50 -> 0 | I68: =1*$E$52 -> 0 | J68: - | K68: 3800 | L68: 3800 | M68: - | N68: =IF(cc_delta>0,cc_delta,0) -> 3800 | O68: =IF(cc_delta<0,ABS(cc_delta),0) -> 0 | P68: - | Q68: 100 | R68: -
E69: Savings | F69: 4 | H69: =1*$E$51 -> 1 | I69: =1*$E$52 -> 0 | J69: - | K69: 1850 | L69: 1850 | M69: - | N69: =IF(cc_delta>0,cc_delta,0) -> 1850 | O69: =IF(cc_delta<0,ABS(cc_delta),0) -> 0 | P69: - | Q69: - | R69: 303
J70: -
D71: =DATE(STARTING_YEAR,5,1) -> 44682 | E71: Income | F71: 5 | H71: =1*$E$49 -> 0 | I71: =1*$E$52 -> 0 | J71: - | K71: 5550 | L71: 5550 | M71: =MIN(cc_tracked,cc_budget) -> 5550 | N71: =IF(cc_delta>0,cc_delta,0) -> 5550 | O71: =IF(cc_delta<0,ABS(cc_delta),0) -> 0 | P71: - | Q71: - | R71: 204
E72: Expenses | F72: 5 | H72: =1*$E$50 -> 0 | I72: =1*$E$52 -> 0 | J72: - | K72: 2900 | L72: 2900 | M72: =MIN(cc_tracked,cc_budget) -> 2900 | N72: =IF(cc_delta>0,cc_delta,0) -> 2900 | O72: =IF(cc_delta<0,ABS(cc_delta),0) -> 0 | P72: - | Q72: 100 | R72: -
E73: Savings | F73: 5 | H73: =1*$E$51 -> 1 | I73: =1*$E$52 -> 0 | J73: - | K73: 2650 | L73: 2650 | M73: =MIN(cc_tracked,cc_budget) -> 2650 | N73: =IF(cc_delta>0,cc_delta,0) -> 2650 | O73: =IF(cc_delta<0,ABS(cc_delta),0) -> 0 | P73: - | Q73: - | R73: 304
J74: -
D75: =DATE(STARTING_YEAR,6,1) -> 44713 | E75: Income | F75: 6 | H75: =1*$E$49 -> 0 | I75: =1*$E$52 -> 0 | J75: - | K75: 5600 | L75: 5600 | M75: =MIN(cc_tracked,cc_budget) -> 5600 | N75: =IF(cc_delta>0,cc_delta,0) -> 5600 | O75: =IF(cc_delta<0,ABS(cc_delta),0) -> 0 | P75: - | Q75: - | R75: 205
E76: Expenses | F76: 6 | H76: =1*$E$50 -> 0 | I76: =1*$E$52 -> 0 | J76: - | K76: 3050 | L76: 3050 | M76: =MIN(cc_tracked,cc_budget) -> 3050 | N76: =IF(cc_delta>0,cc_delta,0) -> 3050 | O76: =IF(cc_delta<0,ABS(cc_delta),0) -> 0 | P76: - | Q76: 100 | R76: -
E77: Savings | F77: 6 | H77: =1*$E$51 -> 1 | I77: =1*$E$52 -> 0 | J77: - | K77: 2550 | L77: 2550 | M77: =MIN(cc_tracked,cc_budget) -> 2550 | N77: =IF(cc_delta>0,cc_delta,0) -> 2550 | O77: =IF(cc_delta<0,ABS(cc_delta),0) -> 0 | P77: - | Q77: - | R77: 305
J78: -
D79: =DATE(STARTING_YEAR,7,1) -> 44743 | E79: Income | F79: 7 | H79: =1*$E$49 -> 0 | I79: =1*$E$52 -> 0 | J79: - | K79: 5650 | L79: 5650 | M79: =MIN(cc_tracked,cc_budget) -> 5650 | N79: =IF(cc_delta>0,cc_delta,0) -> 5650 | O79: =IF(cc_delta<0,ABS(cc_delta),0) -> 0 | P79: - | Q79: - | R79: 206
E80: Expenses | F80: 7 | H80: =1*$E$50 -> 0 | I80: =1*$E$52 -> 0 | J80: - | K80: 2900 | L80: 2900 | M80: =MIN(cc_tracked,cc_budget) -> 2900 | N80: =IF(cc_delta>0,cc_delta,0) -> 2900 | O80: =IF(cc_delta<0,ABS(cc_delta),0) -> 0 | P80: - | Q80: 100 | R80: -
E81: Savings | F81: 7 | H81: =1*$E$51 -> 1 | I81: =1*$E$52 -> 0 | J81: - | K81: 2750 | L81: 2750 | M81: =MIN(cc_tracked,cc_budget) -> 2750 | N81: =IF(cc_delta>0,cc_delta,0) -> 2750 | O81: =IF(cc_delta<0,ABS(cc_delta),0) -> 0 | P81: - | Q81: - | R81: 306
J82: -
D83: =DATE(STARTING_YEAR,8,1) -> 44774 | E83: Income | F83: 8 | H83: =1*$E$49 -> 0 | I83: =1*$E$52 -> 0 | J83: - | K83: 5550 | L83: 5550 | M83: =MIN(cc_tracked,cc_budget) -> 5550 | N83: =IF(cc_delta>0,cc_delta,0) -> 5550 | O83: =IF(cc_delta<0,ABS(cc_delta),0) -> 0 | P83: - | Q83: - | R83: 207
E84: Expenses | F84: 8 | H84: =1*$E$50 -> 0 | I84: =1*$E$52 -> 0 | J84: - | K84: 4100 | L84: 4100 | M84: =MIN(cc_tracked,cc_budget) -> 4100 | N84: =IF(cc_delta>0,cc_delta,0) -> 4100 | O84: =IF(cc_delta<0,ABS(cc_delta),0) -> 0 | P84: - | Q84: 100 | R84: -
E85: Savings | F85: 8 | H85: =1*$E$51 -> 1 | I85: =1*$E$52 -> 0 | J85: - | K85: 1450 | L85: 1450 | M85: =MIN(cc_tracked,cc_budget) -> 1450 | N85: =IF(cc_delta>0,cc_delta,0) -> 1450 | O85: =IF(cc_delta<0,ABS(cc_delta),0) -> 0 | P85: - | Q85: - | R85: 307
J86: -
D87: =DATE(STARTING_YEAR,9,1) -> 44805 | E87: Income | F87: 9 | H87: =1*$E$49 -> 0 | I87: =1*$E$52 -> 0 | J87: - | K87: 5600 | L87: 5600 | M87: =MIN(cc_tracked,cc_budget) -> 5600 | N87: =IF(cc_delta>0,cc_delta,0) -> 5600 | O87: =IF(cc_delta<0,ABS(cc_delta),0) -> 0 | P87: - | Q87: - | R87: 208
E88: Expenses | F88: 9 | H88: =1*$E$50 -> 0 | I88: =1*$E$52 -> 0 | J88: - | K88: 3050 | L88: 3050 | M88: =MIN(cc_tracked,cc_budget) -> 3050 | N88: =IF(cc_delta>0,cc_delta,0) -> 3050 | O88: =IF(cc_delta<0,ABS(cc_delta),0) -> 0 | P88: - | Q88: 100 | R88: -
E89: Savings | F89: 9 | H89: =1*$E$51 -> 1 | I89: =1*$E$52 -> 0 | J89: - | K89: 2550 | L89: 2550 | M89: =MIN(cc_tracked,cc_budget) -> 2550 | N89: =IF(cc_delta>0,cc_delta,0) -> 2550 | O89: =IF(cc_delta<0,ABS(cc_delta),0) -> 0 | P89: - | Q89: - | R89: 308
J90: -
D91: =DATE(STARTING_YEAR,10,1) -> 44835 | E91: Income | F91: 10 | H91: =1*$E$49 -> 0 | I91: =1*$E$52 -> 0 | J91: - | K91: 5650 | L91: 5650 | M91: =MIN(cc_tracked,cc_budget) -> 5650 | N91: =IF(cc_delta>0,cc_delta,0) -> 5650 | O91: =IF(cc_delta<0,ABS(cc_delta),0) -> 0 | P91: - | Q91: - | R91: 209
E92: Expenses | F92: 10 | H92: =1*$E$50 -> 0 | I92: =1*$E$52 -> 0 | J92: - | K92: 2900 | L92: 2900 | M92: =MIN(cc_tracked,cc_budget) -> 2900 | N92: =IF(cc_delta>0,cc_delta,0) -> 2900 | O92: =IF(cc_delta<0,ABS(cc_delta),0) -> 0 | P92: - | Q92: 100 | R92: -
E93: Savings | F93: 10 | H93: =1*$E$51 -> 1 | I93: =1*$E$52 -> 0 | J93: - | K93: 2750 | L93: 2750 | M93: =MIN(cc_tracked,cc_budget) -> 2750 | N93: =IF(cc_delta>0,cc_delta,0) -> 2750 | O93: =IF(cc_delta<0,ABS(cc_delta),0) -> 0 | P93: - | Q93: - | R93: 309
J94: -
D95: =DATE(STARTING_YEAR,11,1) -> 44866 | E95: Income | F95: 11 | H95: =1*$E$49 -> 0 | I95: =1*$E$52 -> 0 | J95: - | K95: 5550 | L95: 5550 | M95: =MIN(cc_tracked,cc_budget) -> 5550 | N95: =IF(cc_delta>0,cc_delta,0) -> 5550 | O95: =IF(cc_delta<0,ABS(cc_delta),0) -> 0 | P95: - | Q95: - | R95: 210
E96: Expenses | F96: 11 | H96: =1*$E$50 -> 0 | I96: =1*$E$52 -> 0 | J96: - | K96: 2900 | L96: 2900 | M96: =MIN(cc_tracked,cc_budget) -> 2900 | N96: =IF(cc_delta>0,cc_delta,0) -> 2900 | O96: =IF(cc_delta<0,ABS(cc_delta),0) -> 0 | P96: - | Q96: 100 | R96: -
E97: Savings | F97: 11 | H97: =1*$E$51 -> 1 | I97: =1*$E$52 -> 0 | J97: - | K97: 2650 | L97: 2650 | M97: =MIN(cc_tracked,cc_budget) -> 2650 | N97: =IF(cc_delta>0,cc_delta,0) -> 2650 | O97: =IF(cc_delta<0,ABS(cc_delta),0) -> 0 | P97: - | Q97: - | R97: 310
J98: -
D99: =DATE(STARTING_YEAR,12,1) -> 44896 | E99: Income | F99: 12 | H99: =1*$E$49 -> 0 | I99: =1*$E$52 -> 0 | J99: - | K99: 5600 | L99: 5600 | M99: =MIN(cc_tracked,cc_budget) -> 5600 | N99: =IF(cc_delta>0,cc_delta,0) -> 5600 | O99: =IF(cc_delta<0,ABS(cc_delta),0) -> 0 | P99: - | Q99: - | R99: 211
E100: Expenses | F100: 12 | H100: =1*$E$50 -> 0 | I100: =1*$E$52 -> 0 | J100: - | K100: 3350 | L100: 3350 | M100: =MIN(cc_tracked,cc_budget) -> 3350 | N100: =IF(cc_delta>0,cc_delta,0) -> 3350 | O100: =IF(cc_delta<0,ABS(cc_delta),0) -> 0 | P100: - | Q100: 100 | R100: -
E101: Savings | F101: 12 | H101: =1*$E$51 -> 1 | I101: =1*$E$52 -> 0 | J101: - | K101: 2250 | L101: 2250 | M101: =MIN(cc_tracked,cc_budget) -> 2250 | N101: =IF(cc_delta>0,cc_delta,0) -> 2250 | O101: =IF(cc_delta<0,ABS(cc_delta),0) -> 0 | P101: - | Q101: - | R101: 311
J102: -
